Workbook

Sheet Insumo
A1: 3 - 705
A2: Cod. Insumo | B2: Desc. Insumo | C2: Unid. Insumo | D2: Preco Insumo | E2: Preco Improd.
A3: IE0001 | B3: TRATOR DE ESTEIRAS : NEW HOLLAND : 7D - COM LÂMINA | C3: H | D3: 123.7328 | E3: 20.5962
A4: IE0002 | B4: TRATOR DE ESTEIRAS : CATERPILLAR : D6N - COM LÂMINA | C4: H | D4: 178.5126 | E4: 20.5962
A5: IE0003 | B5: TRATOR DE ESTEIRAS : CATERPILLAR : D8T - COM LÂMINA | C5: H | D5: 392.9867 | E5: 20.5962
A6: IE0005 | B6: MOTOSCRAPER : CATERPILLAR : 621H - | C6: H | D6: 438.2318 | E6: 20.5962
A7: IE0006 | B7: MOTONIVELADORA : CATERPILLAR : 120K - | C7: H | D7: 153.4794 | E7: 20.5962
A8: IE0007 | B8: TRATOR AGRÍCOLA : MASSEY FERGUSON : MF 4291/4 449A - | C8: H | D8: 72.8389 | E8: 15.4471
A9: IE0009 | B9: CARREGADEIRA DE PNEUS : CATERPILLAR : 924H - 1,80 M3 | C9: H | D9: 123.8771 | E9: 20.5962
A10: IE0010 | B10: CARREGADEIRA DE PNEUS : CATERPILLAR : 950H - 3,3 M3 | C10: H | D10: 204.9757 | E10: 20.5962
A11: IE0011 | B11: RETROESCAVADEIRA : MASSEY FERGUSON : MF-86HS - DE | C11: H | D11: 77.4726 | E11: 20.5962
A12: IE0013 | B12: ROLO COMPACTADOR : DYNAPAC : CA-250-P - PÉ DE CARNEIRO | C12: H | D12: 116.1012 | E12: 15.4471
A13: IE0014 | B13: TRATOR DE ESTEIRAS : CATERPILLAR : D8T - COM | C13: H | D13: 403.4299 | E13: 20.5962
A14: IE0015 | B14: TRATOR DE ESTEIRAS : CATERPILLAR : D8T - COM | C14: H | D14: 195.71 | E14: 20.6
... A227: IH0000 | B227: SALÁRIO MÍNIMO | C227: H | D227: 7.2522 | E227: 0
A228: IH0001 | B228: CAPATAZ | C228: H | D228: 14
A229: IH0002 | B229: MAESTRO 1° | C229: H | D229: 12
A230: IH0003 | B230: MAESTRO 2° | C230: H | D230: 10
A231: IH0004 | B231: AYUDANTE | C231: H | D231: 9
A232: IH0301 | B232: MOTORISTA DE VEÍCULO LEVE | C232: H | D232: 12.1111 | E232: 0
A233: IH0302 | B233: MOTORISTA DE CAMINHÃO | C233: H | D233: 15.8097 | E233: 0
A234: IH0303 | B234: MOTORISTA DE VEÍCULO ESPECIAL | C234: H | D234: 16.2449 | E234: 0
A235: IH0311 | B235: OPERADOR DE EQUIPAMENTO LEVE 1 | C235: H | D235: 15.4471 | E235: 0
A236: IH0312 | B236: OPERADOR DE EQUIPAMENTO LEVE 2 | C236: H | D236: 15.4471 | E236: 0
A237: IH0313 | B237: OPERADOR DE EQUIP. PESADO | C237: H | D237: 20.5962 | E237: 0
A238: IH0314 | B238: OPERADOR DE EQUIP. ESPECIAL | C238: H | D238: 20.6687 | E238: 0
A239: IH0401 | B239: PRÉ-MARCADOR | C239: H | D239: 12.4737 | E239: 0
A240: IH0501 | B240: ENCARREGADO DE TURMA | C240: H | D240: 26.7605 | E240: 0
A241: IH0511 | B241: ENCARREG. DE PAVIMENTAÇÃO | C241: H | D241: 38.5816 | E241: 0
A242: IH0512 | B242: ENCARREGADO DE BRITAGEM | C242: H | D242: 38.5816 | E242: 0
A243: IH0601 | B243: BLASTER | C243: H | D243: 26.7605 | E243: 0
... A260: IM0005 | B260: ENERGIA ELÉTRICA | C260: KWH | D260: 0.48 | E260: 0
A261: IM0006 | B261: LUBRIFICANTES Y GRASAS | C261: KG | D261: =+D257*2.5 -> 5.725 | E261: 0
A262: IM0101 | B262: CIMENTO ASFÁLTICO CAP 50/70 | C262: T | D262: 0 | E262: 0
A263: IM0102 | B263: CIMENTO ASFÁLTICO CAP 30/45 | C263: T | D263: 0 | E263: 0
A264: IM0103 | B264: ASFALTO DILUÍDO CM-30 | C264: T | D264: 0 | E264: 0
A265: IM0104 | B265: EMULSÃO ASFÁLTICA RR-1C | C265: T | D265: 0 | E265: 0
A266: IM0105 | B266: EMULSÃO ASFÁLTICA RR-2C | C266: T | D266: 0 | E266: 0
A267: IM0106 | B267: EMULSÃO ASFALTICA RR1C C/ POLÍMERO | C267: T | D267: 0 | E267: 0
A268: IM0107 | B268: EMULSÃO ASFÁLTICA RM-1C | C268: T | D268: 0 | E268: 0
A269: IM0108 | B269: EMULSÃO ASFÁLTICA RM1C C/ POLÍMERO | C269: T | D269: 0 | E269: 0
A270: IM0109 | B270: EMULSÃO ASFÁLTICA RL-1C | C270: T | D270: 0 | E270: 0
A271: IM0110 | B271: EMULSÃO POLIM. P/ MICRO-REV. A FRIO | C271: T | D271: 0 | E271: 0
A272: IM0111 | B272: ADIFLEX | C272: KG | D272: 3.7 | E272: 0
A273: IM0112 | B273: ADISOL | C273: KG | D273: 4 | E273: 0
... A550: IN0943 | B550: TERRA ARMADA - MOLDES METÁLICOS | C550: M3 | D550: 55.56 | E550: 0
A551: IP0001 | B551: AMORTIZACION EQUIPO | C551: VA | D551: 1
A552: IP0002 | B552: REPUESTOS PARA MAQUINARIA | C552: VA | D552: 1
A553: IP0003 | B553: NEUMATICOS | C553: VA | D553: 1
A554: IT0001 | B554: CIMENTO PORTLAND CP II-32 | C554: T | D554: 0 | E554: 0
A555: IT0002 | B555: RACHÃO OU PEDRA-DE-MÃO PRODUZIDOS-(CONST E REST) | C555: T | D555: 0 | E555: 0
A556: IT0003 | B556: AREIA EXTRAÍDA COM ESCAVADEIRA HIDRÁULICA | C556: T | D556: 0 | E556: 0
A557: IT0004 | B557: PEDRA DE MÃO | C557: T | D557: 0 | E557: 0
A558: IT0005 | B558: AREIA COMERCIAL | C558: T | D558: 0 | E558: 0
A559: IT0006 | B559: CAL HIDRATADA | C559: T | D559: 0 | E559: 0
A560: IT0007 | B560: TIJOLO 20 X 30 CM | C560: T | D560: 0 | E560: 0
A561: IT0008 | B561: BRITA PRODUZIDA EM CENTRAL DE BRITAGEM DE 80 M3/H | C561: T | D561: 0 | E561: 0
A562: IT0009 | B562: BRITA COMERCIAL | C562: T | D562: 0 | E562: 0
A563: IT0010 | B563: ESCAV. E CARGA DE MATER. DE JAZIDA(CONST E RESTR) | C563: T | D563: 0 | E563: 0
A564: IT0011 | B564: USINAGEM DE SOLO-BRITA | C564: T | D564: 0 | E564: 0
A565: IT0012 | B565: USINAGEM DE SOLO-BRITA BC | C565: T | D565: 0 | E565: 0
... A713: IT0160 | B713: USINAGEM DE AGREGADOS P/ MICRO-REVESTIMENTO BC | C713: T | D713: 0 | E713: 0
A714: IV0001 | B714: PROD.VARIOS LOCALES | C714: VA | D714: 1
A718: IE | B718: Macchine
A719: IH | B719: Mano d'opera
A720: IM | B720: Matetriali
A721: IN | B721: ????
A722: IT | B722: ????

Sheet CP. Auxiliar
A1: 4-1196
A2: Cod. Composicao | B2: Descricao Completa | C2: Unid. Comp | D2: Prod. Equipe | E2: Perc. Ferramenta | F2: Cod. Insumo | G2: Qtde Equip. | H2: Indice | I2: Indice Improdutivo | J2: DMT (Transp) | K2: Consumo (Transp) | L2: Unid. Insumo | M2: Desc. Insumo
A3: CA0001 | B3: CUADRILLA ESCAVACION 1 Turno per dia | C3: H | D3: 1 | F3: XXXX | H3: =0.3/10 -> 0.03 | L3: H | M3: CAPATAZ
F4: XXXX | H4: =0.7/10 -> 0.07 | L4: H | M4: MAESTRO 1°
F5: XXXX | H5: =3/10 -> 0.3 | L5: H | M5: MAESTRO 2°
F6: XXXX | H6: =6/10 -> 0.6 | L6: H | M6: AYUDANTE
A7: CA0002 | B7: CUADRILLA ESCAVACION 2 Turno por dia | F7: XXXX | H7: =0.3/10 -> 0.03 | L7: H | M7: CAPATAZ
F8: XXXX | H8: =0.7/10 -> 0.07 | L8: H | M8: MAESTRO 1°
F9: XXXX | H9: =3/10 -> 0.3 | L9: H | M9: MAESTRO 2°
F10: XXXX | H10: =6/10 -> 0.6 | L10: H | M10: AYUDANTE
A11: CA0003 | B11: CUADRILLA CONCRETO 1 Turno por dia | F11: XXXX | H11: 0.1 | L11: H | M11: CAPATAZ
F12: XXXX | H12: 0.2 | L12: H | M12: MAESTRO 1°
F13: XXXX | H13: 0.3 | L13: H | M13: MAESTRO 2°
F14: XXXX | H14: 0.4 | L14: H | M14: AYUDANTE
A15: CA0004 | B15: CUADRILLA CONCRETO 2 Turno por dia | F15: XXXX | H15: 0.1 | L15: H | M15: CAPATAZ
F16: XXXX | H16: 0.2 | L16: H | M16: MAESTRO 1°
F17: XXXX | H17: 0.3 | L17: H | M17: MAESTRO 2°
F18: XXXX | H18: 0.4 | L18: H | M18: AYUDANTE
A19: CA0005 | B19: CUADRILLA FORMALETA 1 Turno por dia | F19: XXXX | H19: 0.1 | L19: H | M19: CAPATAZ
F20: XXXX | H20: 0.3 | L20: H | M20: MAESTRO 1°
F21: XXXX | H21: 0.3 | L21: H | M21: MAESTRO 2°
F22: XXXX | H22: 0.3 | L22: H | M22: AYUDANTE
A23: CA0006 | B23: CUADRILLA FORMALETA 2 Turno por dia | F23: XXXX | H23: 0.1 | L23: H | M23: CAPATAZ
F24: XXXX | H24: 0.3 | L24: H | M24: MAESTRO 1°
F25: XXXX | H25: 0.3 | L25: H | M25: MAESTRO 2°
F26: XXXX | H26: 0.3 | L26: H | M26: AYUDANTE
A27: CA0007 | B27: CUADRILLA ACERO 1 Turno por dia | F27: XXXX | H27: 0.1 | L27: H | M27: CAPATAZ
F28: XXXX | H28: 0.2 | L28: H | M28: MAESTRO 1°
F29: XXXX | H29: 0.4 | L29: H | M29: MAESTRO 2°
F30: XXXX | H30: 0.3 | L30: H | M30: AYUDANTE
A31: CA0008 | B31: CUADRILLA ACERO 2 Turno por dia | F31: XXXX | H31: 0.1 | L31: H | M31: CAPATAZ
F32: XXXX | H32: 0.2 | L32: H | M32: MAESTRO 1°
F33: XXXX | H33: 0.4 | L33: H | M33: MAESTRO 2°
F34: XXXX | H34: 0.3 | L34: H | M34: AYUDANTE
A35: CA0009 | B35: CUADRILLA VARIOS 1 Turno por dia | F35: XXXX | H35: 0.1 | L35: H | M35: CAPATAZ
F36: XXXX | H36: 0.2 | L36: H | M36: MAESTRO 1°
F37: XXXX | H37: 0.2 | L37: H | M37: MAESTRO 2°
F38: XXXX | H38: 0.5 | L38: H | M38: AYUDANTE
A39: CA0010 | B39: CUADRILLA VARIOS 2 Turno por dia | F39: XXXX | H39: 0.1 | L39: H | M39: CAPATAZ
F40: XXXX | H40: 0.2 | L40: H | M40: MAESTRO 1°
F41: XXXX | H41: 0.2 | L41: H | M41: MAESTRO 2°
F42: XXXX | H42: 0.5 | L42: H | M42: AYUDANTE
A43: CA0010 | B43: CUADRILLA VARIOS 2 Turno por dia | F43: XXXX | H43: 0.1 | L43: H | M43: CAPATAZ
F44: XXXX | H44: 0.2 | L44: H | M44: MAESTRO 1°
F45: XXXX | H45: 0.2 | L45: H | M45: MAESTRO 2°
F46: XXXX | H46: 0.5 | L46: H | M46: AYUDANTE
A47: CA0015 | B47: M / S Formaleta
F48: =+A19 -> CA0005 | H48: =2*2*4900/145036 -> 0.13513886 | M48: CUADRILLA FORMALETA 1 Turno por dia
F49: XXXX | H49: =0.01*2*4900/145036 -> 0.00067569431 | I49: =(H49/0.6)-H49 -> 0.00045046287 | M49: CAMION PLATAFORMA CON GRUA 5 TON
F50: XXXX | H50: =0.02*2*4900/145036 -> 0.0013513886 | I50: =(H50/0.6)-H50 -> 0.00090092575 | M50: Grua su pneumatico 35 ton
F51: XXXX | H51: =0.04*2*4900/145036 -> 0.0027027772 | I51: =(H51/0.6)-H51 -> 0.0018018515 | M51: Fork . Lift
F52: XXXX | H52: =SUM(H49:I51) -> 0.0078831003 | M52: OPERADOR DE EQUIP. PESADO 1 turno por dia
F53: =+A77 -> CA0052 | H53: =0.02*2*4900/145036 -> 0.0013513886 | M53: AQUA
F54: XXXX | H54: =0.0058*2*4900/145036 -> 0.0003919027 | M54: COMPRESOR DIESEL 11 MC/MIN
F55: XXXX | H55: =0.0009*2*4900/145036 -> 6.0812488e-05 | M55: Saldadora diesel 550 AMP
F56: XXXX | H56: =85/145036 -> 0.00058606139 | M56: Madera comun
A57: CA0016 | B57: CURING
F58: =+A23 -> CA0006 | H58: 0.08 | M58: CUADRILLA FORMALETA 2 Turno por dia
F59: XXXX | H59: 0.0035 | I59: =(H59/0.7)-H59 -> 0.0015 | M59: Grua su pneumatico 35 ton
F60: XXXX | H60: 0.014 | I60: =(H60/0.7)-H60 -> 0.006 | M60: Fork . Lift
F61: XXXX | H61: =SUM(H59:I60) -> 0.025 | M61: OPERADOR DE EQUIP. PESADO 1 turno por dia
F62: =+A77 -> CA0052 | H62: 0.2 | M62: AQUA
F63: XXXX | H63: 0.017 | I63: =(H63/0.7)-H63 -> 0.0072857143 | M63: CAMION PARA AQUA 18000 LIT
F64: XXXXX | H64: =SUM(H63:I63) -> 0.024285714 | M64: OPERADOR DE EQUIP. PESADO 2 turno por dia
F65: XXXX | H65: 0.021 | M65: COMPRESOR DIESEL 11 MC/MIN
A69: CA0050 | B69: ENERGIA ELECTRICA
A73: CA0051 | B73: ILLUMINAZIONE
A77: CA0052 | B77: AQUA
A81: CA0053 | B81: DEWATERING
A85: CA0053 | B85: DEWATERING

Sheet CP. Principal
A2: Cod. Composicao | B2: Descricao Completa | C2: Unid. Comp | D2: Prod. Equipe | E2: Perc. Ferramenta | F2: Cod. Insumo | G2: código | H2: Qtde Equip. | I2: Indice | J2: Indice Improdutivo | K2: DMT (Transp) | L2: Consumo (Transp) | M2: Unid. Insumo | N2: Desc. Insumo | O2: NOTE
A4: CB0001 | B4: 25.6 BARRA DE ACO CA-50 | C4: KG | D4: 1 | F4: XXXX | I4: 1.05 | N4: ACERO CORTADO E DOBLADO PER PANTALLAS IN SITE C-50 | O4: doca seca - SOLO OPERAZIONI DI SCARICO POSA NEL COSTO DEL DIAFRAMMA
F5: =+'CP. Auxiliar'!A31 -> CA0008 | I5: =+I6*10*1.2 -> 0.0010152 | N5: =+'CP. Auxiliar'!B31 -> CUADRILLA ACERO 2 Turno por dia
F6: XXXX | G6: IE5068 | I6: =0.0846/1000 -> 8.46e-05 | J6: =(I5/10)-I6 -> 1.692e-05 | N6: GRU CINGOLATA 50 TON
F7: XXXX | G7: IH1021 | I7: =I6+J6 -> 0.00010152 | N7: OPERADOR DE EQUIP. PESADO 2 turno por dia
F8: =+'CP. Auxiliar'!A73 -> CA0051 | G8: IE5077 | I8: 1.5e-05 | J8: =+I8 -> 1.5e-05 | M8: HR | N8: =+'CP. Auxiliar'!B73 -> ILLUMINAZIONE
A9: CB0002 | B9: 5.13 BARRA DE ACO CA-50 | C9: KG | F9: XXXX | I9: =1.05*S10 -> 0.525 | N9: ACERO CORTADO E DOBLADO PER PANTALLAS IN SITE C-50 | O9: rampe di accesso paratie | S9: % PARATIE | T9: % CLS NORMALE
F10: =+F5 -> CA0008 | I10: =+I11*10*1.2 -> 0.0005076 | N10: =+N5 -> CUADRILLA ACERO 2 Turno por dia | S10: 0.5 | T10: 0.5
F11: XXXX | G11: IE5068 | I11: =(0.0846/1000)*S10 -> 4.23e-05 | J11: =(I10/10)-I11 -> 8.46e-06 | N11: GRU CINGOLATA 50 TON
F12: XXXX | G12: IH1021 | I12: =I11+J11 -> 5.076e-05 | N12: OPERADOR DE EQUIP. PESADO 2 turno por dia
F13: =+F8 -> CA0051 | G13: IE5077 | I13: 1.5e-05 | J13: =+I13 -> 1.5e-05 | M13: HR | N13: =+N8 -> ILLUMINAZIONE
F14: XXXX | I14: =1.05*T10 -> 0.525 | N14: ACERO CORTADO E DOBLADO IN SITE C-50 | O14: acciao per calcerstruzzi normali
F15: =+'CP. Auxiliar'!A31 -> CA0008 | I15: =(100*T10)/1000 -> 0.05 | N15: =+N10 -> CUADRILLA ACERO 2 Turno por dia
F16: XXXX | G16: IE5010 | I16: =((0.29+0.0846+0.0846)/1000)*T10 -> 0.0002296 | J16: =+I17-I16 -> 0.0047704 | N16: Grua da 35 Ton
F17: XXXX | G17: IH1021 | I17: =I15/10 -> 0.005 | N17: OPERADOR DE EQUIP. PESADO 2 turno por dia
F18: XXXX | G18: IE5076 | I18: =(0.17/1000)*T10 -> 8.5e-05 | J18: =+I19-I18 -> 0.002415 | N18: Camion con baja da 40 ton
F19: XXXX | G19: IH1021 | I19: =(I15/10)*0.5 -> 0.0025 | N19: OPERADOR DE EQUIP. PESADO 2 turno por dia | O19: Considero che il camion al 50 % perché farà altri lavori
F20: XXXX | G20: IE5049 | I20: =(0.31/1000)*T10 -> 0.000155 | J20: =(I15/10)-I20 -> 0.004845 | N20: Saldadora diesel 550 AMP
F21: =+'CP. Auxiliar'!A73 -> CA0051 | G21: IE5077 | I21: 1.5e-05 | J21: =+I21 -> 1.5e-05 | M21: HR | N21: =+'CP. Auxiliar'!B73 -> ILLUMINAZIONE
A22: CB0003 | B22: 6.11 BARRA DE ACO CA - 50 | C22: KG | F22: XXXX | I22: 1.05 | N22: ACERO CORTADO E DOBLADO PER PANTALLAS IN SITE C-50
F23: =+'CP. Auxiliar'!A31 -> CA0008 | I23: =100/1000 -> 0.1 | N23: =+'CP. Auxiliar'!B31 -> CUADRILLA ACERO 2 Turno por dia
F24: XXXX | G24: IE5010 | I24: =(0.29+0.0846+0.0846)/1000 -> 0.0004592 | J24: =+I25-I24 -> 0.0095408 | N24: Grua da 35 Ton
F25: XXXX | G25: IH1021 | I25: =I23/10 -> 0.01 | N25: OPERADOR DE EQUIP. PESADO 2 turno por dia
F26: XXXX | G26: IE5076 | I26: =(0.17/1000) -> 0.00017 | J26: =+I27-I26 -> 0.00483 | N26: Camion con baja da 40 ton
F27: XXXX | G27: IH1021 | I27: =(I23/10)*0.5 -> 0.005 | N27: OPERADOR DE EQUIP. PESADO 2 turno por dia | O27: Considero che il camion al 50 % perché farà altri lavori
F28: XXXX | G28: IE5049 | I28: =(0.31/1000) -> 0.00031 | J28: =(I23/10)-I28 -> 0.00969 | N28: Saldadora diesel 550 AMP
F29: =+'CP. Auxiliar'!A73 -> CA0051 | G29: IE5077 | I29: 1.5e-05 | J29: =+I29 -> 1.5e-05 | M29: HR | N29: ILLUMINAZIONE
A30: CB0004 | B30: 25.7 BARRA DE ACO CA - 60 | C30: KG | F30: XXXX | I30: 1.05 | N30: ACERO CORTADO E DOBLADO IN SITE C-60
F31: =+'CP. Auxiliar'!A39 -> CA0010 | I31: =100/1000 -> 0.1 | N31: =+'CP. Auxiliar'!B39 -> CUADRILLA VARIOS 2 Turno por dia
F32: XXXX | G32: IE5010 | I32: =(0.29+0.0846+0.0846)/1000 -> 0.0004592 | J32: =+I33-I32 -> 0.0095408 | N32: Grua da 35 Ton
F33: XXXX | G33: IH1021 | I33: =I31/10 -> 0.01 | N33: OPERADOR DE EQUIP. PESADO 2 turno por dia
F34: XXXX | G34: IE5076 | I34: =(0.17/1000) -> 0.00017 | J34: =+I35-I34 -> 0.00483 | N34: Camion con baja da 40 ton
F35: XXXX | G35: IH1021 | I35: =(I31/10)*0.5 -> 0.005 | N35: OPERADOR DE EQUIP. PESADO 2 turno por dia | O35: Considero che il camion al 50 % perché farà altri lavori
F36: XXXX | G36: IE5049 | I36: =(0.31/1000) -> 0.00031 | J36: =(I31/10)-I36 -> 0.00969 | N36: Saldadora diesel 550 AMP
F37: =+'CP. Auxiliar'!A73 -> CA0051 | G37: IE5077 | I37: 1.5e-05 | J37: =+I37 -> 1.5e-05 | M37: HR | N37: ILLUMINAZIONE
A38: CB0005 | B38: 6.12 BARRA DE ACO CA - 60 | C38: KG | F38: XXXX | I38: 1.05 | N38: ACERO CORTADO E DOBLADO IN SITE C-60
F39: =+'CP. Auxiliar'!A31 -> CA0008 | I39: =100/1000 -> 0.1 | N39: =+'CP. Auxiliar'!B31 -> CUADRILLA ACERO 2 Turno por dia
F40: XXXX | G40: IE5010 | I40: =(0.29+0.0846+0.0846)/1000 -> 0.0004592 | J40: =+I41-I40 -> 0.0095408 | N40: Grua da 35 Ton
F41: XXXX | G41: IH1021 | I41: =I39/10 -> 0.01 | N41: OPERADOR DE EQUIP. PESADO 2 turno por dia
F42: XXXX | G42: IE5076 | I42: =(0.17/1000) -> 0.00017 | J42: =+I43-I42 -> 0.00483 | N42: Camion con baja da 40 ton | O42: Considero che il camion al 50 % perché farà altri lavori
F43: XXXX | G43: IH0313 | I43: =(I39/10)*0.5 -> 0.005 | N43: OPERADOR DE EQUIP. PESADO
F44: XXXX | G44: IE5049 | I44: =(0.31/1000) -> 0.00031 | J44: =(I39/10)-I44 -> 0.00969 | N44: Saldadora diesel 550 AMP
F45: =+'CP. Auxiliar'!A73 -> CA0051 | G45: IE5077 | I45: 1.5e-05 | J45: =+I45 -> 1.5e-05 | M45: HR | N45: ILLUMINAZIONE
A46: CB0006 | B46: 6.10 BARRA DE ACO CA - 25 | C46: KG | F46: XXXX | I46: 1.05 | N46: ACERO CORTADO E DOBLADO IN SITE C-25
F47: =+'CP. Auxiliar'!A31 -> CA0008 | I47: =100/1000 -> 0.1 | N47: =+'CP. Auxiliar'!B31 -> CUADRILLA ACERO 2 Turno por dia
F48: XXXX | G48: IE5010 | I48: =(0.29+0.0846+0.0846)/1000 -> 0.0004592 | J48: =+I49-I48 -> 0.0095408 | N48: Grua da 35 Ton
F49: XXXX | G49: IH1021 | I49: =I47/10 -> 0.01 | N49: OPERADOR DE EQUIP. PESADO 2 turno por dia
F50: XXXX | G50: IE5076 | I50: =(0.17/1000) -> 0.00017 | J50: =+I51-I50 -> 0.00483 | N50: Camion con baja da 40 ton
F51: XXXX | G51: IH1021 | I51: =(I47/10)*0.5 -> 0.005 | N51: OPERADOR DE EQUIP. PESADO 2 turno por dia | O51: Considero che il camion al 50 % perché farà altri lavori
F52: XXXX | G52: IE5049 | I52: =(0.31/1000) -> 0.00031 | J52: =(I47/10)-I52 -> 0.00969 | N52: Saldadora diesel 550 AMP
F53: =+'CP. Auxiliar'!A73 -> CA0051 | G53: IE5077 | I53: 1.5e-05 | J53: =+I53 -> 1.5e-05 | M53: HR | N53: ILLUMINAZIONE
A54: CB0007 | B54: 6.23 CONCRETO fck 35 Mpa | C54: MC | F54: CA0468 | I54: 1.05 | N54: CONCRETO fck 35 Mpa | O54: IL POMPAGGIO DEL CLS è PAGATO A PARTE
F55: CA0509 | G55: IE5001 | I55: 1.05 | N55: CENTRAL DOSADORA DE CONCRETO
F56: =+'CP. Auxiliar'!A15 -> CA0004 | I56: 2.1 | N56: =+'CP. Auxiliar'!B15 -> CUADRILLA CONCRETO 2 Turno por dia
E57: IE0427 | F57: XXXXX | G57: IE5008 | I57: 0.15 | J57: =(I57/0.8)-I57 -> 0.0375 | N57: HORMIGONERA 8 MC
F58: XXXX | G58: IH1021 | I58: =+I57+J57 -> 0.1875 | N58: OPERADOR DE EQUIP. PESADO 2 turno por dia
F59: XXXX | G59: IE0306 | I59: 0.126 | J59: =((I56/10))*3-I59 -> 0.504 | N59: VIBRADOR PER CONCRETO 75 MM AD AIRE
F60: XXXX | G60: IE0202 | I60: =+I59/3 -> 0.042 | J60: =(I56/10)-I60 -> 0.168 | N60: COMPRESOR DIESEL 11 MC/MIN
F61: =+'CP. Auxiliar'!A77 -> CA0052 | G61: IM1070 | I61: 0.4 | N61: =+'CP. Auxiliar'!B77 -> AQUA
F62: XXXX | G62: IE0406 | I62: 0.033 | J62: =((I56/10)*0.5)-I62 -> 0.072 | N62: CAMION PARA AQUA 18000 LIT | O62: Considero che il camion al 50 % perché farà altri lavori
F63: XXXX | G63: IH1021 | I63: =+I62+J62 -> 0.105 | N63: OPERADOR DE EQUIP. PESADO 2 turno por dia
F64: XXXX | G64: IE0202 | I64: 0.0167 | J64: =(I56/10)-I64 -> 0.1933 | N64: COMPRESOR DIESEL 11 MC/MIN
F65: =+'CP. Auxiliar'!A73 -> CA0051 | G65: IE5077 | I65: 0.0047 | J65: =+I65 -> 0.0047 | M65: HR | N65: ILLUMINAZIONE
A66: CB0008 | B66: 5.15 CONCRETO fck 15 Mpa | C66: MC | F66: CA0464 | I66: 1.08 | N66: CONCRETO fck 15 Mpa
F67: CA0509 | G67: IE5001 | I67: 1.08 | N67: CENTRAL DOSADORA DE CONCRETO
F68: =+'CP. Auxiliar'!A15 -> CA0004 | I68: 0.9 | N68: =+'CP. Auxiliar'!B15 -> CUADRILLA CONCRETO 2 Turno por dia
E69: IE0427 | F69: XXXX | G69: IE5008 | I69: 0.15 | J69: =(I69/0.8)-I69 -> 0.0375 | N69: HORMIGONERA 8 MC
F70: XXXX | G70: IH1021 | I70: =+I69+J69 -> 0.1875 | N70: OPERADOR DE EQUIP. PESADO 2 turno por dia
F71: XXXX | G71: IE0306 | I71: 0.054 | J71: =((I68/10)*3)-I71 -> 0.216 | N71: VIBRADOR PER CONCRETO 75 MM AD AIRE
F72: XXXX | G72: IE0202 | I72: =+I71/3 -> 0.018 | J72: =(I68/10)-I72 -> 0.072 | N72: COMPRESOR DIESEL 11 MC/MIN
F73: =+'CP. Auxiliar'!A77 -> CA0052 | G73: IM1070 | I73: 0.1 | N73: =+'CP. Auxiliar'!B77 -> AQUA
F74: XXXX | G74: IE0406 | I74: 0.0083 | J74: =((I68/10)*0.5)-I74 -> 0.0367 | N74: CAMION PARA AQUA 18000 LIT | O74: Considero che il camion al 50 % perché farà altri lavori
F75: XXXX | G75: IH1021 | I75: =+I74+J74 -> 0.045 | N75: OPERADOR DE EQUIP. PESADO 2 turno por dia
F76: XXXX | G76: IE0202 | I76: 0.0063 | J76: =(I68/10)-I76 -> 0.0837 | N76: COMPRESOR DIESEL 11 MC/MIN
F77: =+'CP. Auxiliar'!A73 -> CA0051 | G77: IE5077 | I77: 0.0047 | J77: =+I77 -> 0.0047 | M77: HR | N77: ILLUMINAZIONE
A78: CB0009 | B78: 6.21 CONCRETO fck 30 Mpa | C78: MC | F78: CA0467 | I78: 1.05 | N78: CONCRETO fck 30 Mpa
F79: CA0509 | G79: IE5001 | I79: 1.05 | N79: CENTRAL DOSADORA DE CONCRETO
F80: =+'CP. Auxiliar'!A15 -> CA0004 | I80: 2.25 | N80: =+'CP. Auxiliar'!B15 -> CUADRILLA CONCRETO 2 Turno por dia
E81: IE0427 | F81: XXXX | G81: IE5008 | I81: 0.15 | J81: =(I81/0.8)-I81 -> 0.0375 | N81: HORMIGONERA 8 MC
F82: XXXX | G82: IH1021 | I82: =+I81+J81 -> 0.1875 | N82: OPERADOR DE EQUIP. PESADO 2 turno por dia
F83: XXXX | G83: IE0306 | I83: 0.135 | J83: =((I80/10)*3)-I83 -> 0.54 | N83: VIBRADOR PER CONCRETO 75 MM AD AIRE
F84: XXXX | G84: IE0202 | I84: =+I83/3 -> 0.045 | J84: =(I80/10)-I84 -> 0.18 | N84: COMPRESOR DIESEL 11 MC/MIN
F85: =+'CP. Auxiliar'!A77 -> CA0052 | G85: IM1070 | I85: 0.4 | N85: =+'CP. Auxiliar'!B77 -> AQUA
F86: XXXX | G86: IE0406 | I86: 0.0333 | J86: =((I80/10)*0.5)-I86 -> 0.0792 | N86: CAMION PARA AQUA 18000 LIT | O86: Considero che il camion al 50 % perché farà altri lavori
F87: XXXX | G87: IH1021 | I87: =+I86+J86 -> 0.1125 | N87: OPERADOR DE EQUIP. PESADO 2 turno por dia
F88: XXXX | G88: IE0202 | I88: 0.0167 | J88: =(I80/10)-I88 -> 0.2083 | N88: COMPRESOR DIESEL 11 MC/MIN
F89: =+'CP. Auxiliar'!A73 -> CA0051 | G89: IE5077 | I89: 0.0047 | J89: =+I89 -> 0.0047 | M89: HR | N89: ILLUMINAZIONE
A90: CB0010 | B90: 6.19 CONCRETO fck 10 Mpa | C90: MC | F90: CA0463 | I90: 1.05 | N90: CONCRETO fck 10 Mpa
F91: CA0509 | G91: IE5001 | I91: 1.05 | N91: CENTRAL DOSADORA DE CONCRETO
E92: IE0427 | F92: XXXX | G92: IE5008 | I92: 0.15 | J92: =(I92/0.8)-I92 -> 0.0375 | N92: HORMIGONERA 8 MC
F93: XXXX | G93: IH1021 | I93: =+I92+J92 -> 0.1875 | N93: OPERADOR DE EQUIP. PESADO 2 turno por dia
F94: =+'CP. Auxiliar'!A15 -> CA0004 | I94: 0.9 | N94: =+'CP. Auxiliar'!B15 -> CUADRILLA CONCRETO 2 Turno por dia
F95: =+'CP. Auxiliar'!A77 -> CA0052 | G95: IM1070 | I95: 0.1 | N95: =+'CP. Auxiliar'!B77 -> AQUA
F96: XXXX | G96: IE0406 | I96: 0.0083 | J96: =((I94/10)*0.5)-I96 -> 0.0367 | N96: CAMION PARA AQUA 18000 LIT | O96: Considero che il camion al 50 % perché farà altri lavori
F97: XXXX | G97: IH1021 | I97: =+I96+J96 -> 0.045 | N97: OPERADOR DE EQUIP. PESADO 2 turno por dia
F98: XXXX | G98: IE0202 | I98: 0.0063 | N98: COMPRESOR DIESEL 11 MC/MIN
F99: =+'CP. Auxiliar'!A73 -> CA0051 | G99: IE5077 | I99: 0.0047 | J99: =+I99 -> 0.0047 | M99: HR | N99: ILLUMINAZIONE
A100: CB0011 | B100: 5.17 CONCRETO fck 35 Mpa | C100: MC | F100: CA0468 | I100: 1.22 | N100: CONCRETO fck 35 MPa | O100: Calcestruzzo per le paratie
F101: CA0509 | G101: IE5001 | I101: 1.22 | N101: CENTRAL DOSADORA DE CONCRETO
E102: IE0427 | F102: XXXX | G102: IE5008 | I102: 0.15 | J102: =(I102/0.8)-I102 -> 0.0375 | N102: HORMIGONERA 8 MC
...

Sheet Planilha de serviços
A1: 8-863 | B1: A - F
A2: DATA BASE: SETEMBRO/2013
A3: LPI 001/2013
A4: ORÇAMENTO ESTIMATIVO DE SERVIÇOS E PREÇOS
A5: OBRAS DE IMPLANTAÇÃO DO SUBMERSO - TÚNEL SANTOS - GUARUJÁ, INTEGRANTE DO PROJETO DE MELHORIA LOGÍSTICA E DE MOBILIDADE URBANA ENTRE SANTOS E GUARUJÁ.
A8: ITEM | B8: CPU | C8: DESCRIÇÃO COMPLETA | D8: UNIDADE | E8: QUANT. | F8: PREÇO UNITÁRIO | H8: PREÇO UNITÁRIO DERSA | I8: PREÇO TOTAL | J8: ITEM | K8: SUB GRUPO | L8: CÓDIGO DERSA
C9: ACESSOS - LADO SANTOS E GUARUJÁ
A10: 1 | C10: =K10 -> SERVIÇOS PRELIMINARES | J10: ACESSOS - LADO SANTOS E GUARUJÁ | K10: SERVIÇOS PRELIMINARES | L10: 21
A11: 1.1 | C11: REMOÇÃO CERCA ARAME, INCLUSIVE TRANSPORTE | D11: m | E11: 400 | H11: 12.03 | I11: =E11*H11 -> 4812 | J11: ACESSOS - LADO SANTOS E GUARUJÁ | K11: SERVIÇOS PRELIMINARES | L11: 21.03.01
A12: 1.2 | C12: REMOCAO DE DEFENSA METALICA SIMPLES | D12: m | E12: 200 | H12: 43.91 | I12: =E12*H12 -> 8782 | J12: ACESSOS - LADO SANTOS E GUARUJÁ | K12: SERVIÇOS PRELIMINARES | L12: 21.03.02
A13: 1.3 | C13: REMOÇÃO E TRANSPORTE DE GUIA PRÉ-MOLDADA | D13: m | E13: 18670.46 | H13: 17.64 | I13: =E13*H13 -> 329346.91 | J13: ACESSOS - LADO SANTOS E GUARUJÁ | K13: SERVIÇOS PRELIMINARES | L13: 21.03.08
A14: 1.4 | C14: DEMOLIÇÃO DE CONCRETO ARMADO | D14: m3 | E14: 39039.41 | H14: 294.37 | I14: =E14*H14 -> 11492031 | J14: ACESSOS - LADO SANTOS E GUARUJÁ | K14: SERVIÇOS PRELIMINARES | L14: 21.88.0.,01
A15: 1.5 | C15: DEMOLIÇÃO DE CONCRETO SIMPLES | D15: m3 | E15: 63709.51 | H15: 154.29 | I15: =(E15*H15)-0.008 -> 9829740.3 | J15: ACESSOS - LADO SANTOS E GUARUJÁ | K15: SERVIÇOS PRELIMINARES | L15: 21.88.05.02
A16: 1.6 | C16: DEMOLIÇÃO DE EDIFICAÇÃO EM ALVENARIA | D16: m2 | E16: 66412.68 | H16: 35.6 | I16: =E16*H16 -> 2364291.4 | J16: ACESSOS - LADO SANTOS E GUARUJÁ | K16: SERVIÇOS PRELIMINARES | L16: 21.88.05.05
A17: 1.7 | C17: DEMOLIÇÃO DE EDIFICAÇÃO EM MADEIRA | D17: m2 | E17: 34516.27 | H17: 13.19 | I17: =E17*H17 -> 455269.6 | J17: ACESSOS - LADO SANTOS E GUARUJÁ | K17: SERVIÇOS PRELIMINARES | L17: 21.88.05.06
A18: 1.8 | C18: DEMOLIÇÃO DE PAVIMENTO FLEXIVEL | D18: m3 | E18: 41618.81 | H18: 18.52 | I18: =E18*H18 -> 770780.36 | J18: ACESSOS - LADO SANTOS E GUARUJÁ | K18: SERVIÇOS PRELIMINARES | L18: 21.88.05.07
A19: 1.9 | C19: MURO DE FECHAMENTO COM PLACAS E MOURÕES PRÉ-MOLDADO H=2,00 m | D19: m | E19: 100 | H19: 125.96 | I19: =E19*H19 -> 12596 | J19: ACESSOS - LADO SANTOS E GUARUJÁ | K19: SERVIÇOS PRELIMINARES | L19: 21.88.19.01
A20: 1.10 | C20: TRANSPORTE DE MATERIAL CLASSE IIA e IIB PARA BOTA-FORA ESPECIAL | D20: ton x km | E20: 7813575.8 | H20: 1.24 | I20: =E20*H20 -> 9688834 | J20: ACESSOS - LADO SANTOS E GUARUJÁ | K20: SERVIÇOS PRELIMINARES | L20: 21.88.19.08.03
A21: 1.11 | C21: BRITAGEM DE MATERIAL DE DEMOLIÇÃO | D21: m3 | E21: 101234.38 | H21: 50.86 | I21: =E21*H21 -> 5148780.6 | J21: ACESSOS - LADO SANTOS E GUARUJÁ | K21: SERVIÇOS PRELIMINARES | L21: 21.88.20.01
A22: 1.12 | C22: DEPOSIÇÃO DE MATERIAL CLASSE IIA, EM BOTA-FORA ESPECIAL | D22: ton | E22: 151405.85 | H22: 94.5 | I22: =E22*H22 -> 14307853 | J22: ACESSOS - LADO SANTOS E GUARUJÁ | K22: SERVIÇOS PRELIMINARES | L22: 21.88.21.02
A23: 1.13 | C23: DEPOSIÇÃO DE MATERIAL CLASSE IIB, EM BOTA-FORA ESPECIAL | D23: ton | E23: 151401.71 | H23: 67.5 | I23: =E23*H23 -> 10219615 | J23: ACESSOS - LADO SANTOS E GUARUJÁ | K23: SERVIÇOS PRELIMINARES | L23: 21.88.21.03
A24: 1.14 | C24: TRANSPORTE DE MATERIAL DE DEMOLIÇÃO ATÉ 5 KM | D24: m3 x km | E24: 506171.91 | H24: 1.71 | I24: =E24*H24 -> 865553.97 | J24: ACESSOS - LADO SANTOS E GUARUJÁ | K24: SERVIÇOS PRELIMINARES | L24: 22.88.03.03
A25: 2 | C25: =K25 -> TERRAPLENAGEM | J25: ACESSOS - LADO SANTOS E GUARUJÁ | K25: TERRAPLENAGEM | L25: 22
A26: 2.1 | C26: LIMPEZA ÁRVORES DE TERRENO SEM DESTOCAMENTO DE ÁRVORES | D26: m2 | E26: 181263 | H26: 0.28 | I26: =E26*H26 -> 50753.64 | J26: ACESSOS - LADO SANTOS E GUARUJÁ | K26: TERRAPLENAGEM | L26: 22.01.01
A27: 2.2 | B27: CB0001 | C27: ESCAVAÇÃO E CARGA DE MATERIAL DE 1ª/2ª CATEGORIA | D27: m3 | E27: 49049.95 | H27: 4.9 | I27: =E27*H27 -> 240344.76 | J27: ACESSOS - LADO SANTOS E GUARUJÁ | K27: TERRAPLENAGEM | L27: 22.02.01
A28: 2.3 | C28: ESCAVAÇÃO E CARGA DE MATERIAL DE 2ª CATEGORIA COM RIPPER | D28: m3 | E28: 691.55 | H28: 5.44 | I28: =E28*H28 -> 3762.032 | J28: ACESSOS - LADO SANTOS E GUARUJÁ | K28: TERRAPLENAGEM | L28: 22.02.02
A29: 2.4 | C29: CARGA DE MATERIAL DE LIMPEZA | D29: m3 | E29: 36252.6 | H29: 2.26 | I29: =E29*H29 -> 81930.876 | J29: ACESSOS - LADO SANTOS E GUARUJÁ | K29: TERRAPLENAGEM | L29: 22.02.06
A30: 2.5 | C30: TRANSPORTE DE MATERIAL DE 1ª/2ª CATEGORIA ATÉ 1 km | D30: m3 x km | E30: 729.26 | H30: 3.74 | I30: =E30*H30 -> 2727.4324 | J30: ACESSOS - LADO SANTOS E GUARUJÁ | K30: TERRAPLENAGEM | L30: 22.03.01
A31: 2.6 | C31: TRANSPORTE DE MATERIAL DE 1ª/2ª CATEGORIA ATÉ 2 km | D31: m3 x km | E31: 2187.76 | H31: 2.2 | I31: =E31*H31 -> 4813.072 | J31: ACESSOS - LADO SANTOS E GUARUJÁ | K31: TERRAPLENAGEM | L31: 22.03.02
A32: 2.7 | C32: TRANSPORTE DE MATERIAL DE 1ª/2ª CATEGORIA ATÉ 5 km | D32: m3 x km | E32: 3000.93 | H32: 1.71 | I32: =E32*H32 -> 5131.5903 | J32: ACESSOS - LADO SANTOS E GUARUJÁ | K32: TERRAPLENAGEM | L32: 22.03.03
A33: 2.8 | B33: CB0002 | C33: TRANSPORTE DE MATERIAL DE 1ª/2ª CATEGORIA ATÉ 10 km | D33: m3 x km | E33: 247956.53 | H33: 1.43 | I33: =E33*H33 -> 354577.84 | J33: ACESSOS - LADO SANTOS E GUARUJÁ | K33: TERRAPLENAGEM | L33: 22.03.04
A34: 2.9 | C34: TRANSPORTE DE MATERIAL DE 1ª/2ª CATEGORIA ATÉ 15 km | D34: m3 x km | E34: 63019.43 | H34: 1.26 | I34: =E34*H34 -> 79404.482 | J34: ACESSOS - LADO SANTOS E GUARUJÁ | K34: TERRAPLENAGEM | L34: 22.03.05
A35: 2.10 | C35: TRANSPORTE DE MATERIAL DE LIMPEZA ATÉ 5 km | D35: m3 x km | E35: 35550.75 | H35: 1.93 | I35: =E35*H35 -> 68612.947 | J35: ACESSOS - LADO SANTOS E GUARUJÁ | K35: TERRAPLENAGEM | L35: 22.88.03.12.01
A36: 2.11 | C36: TRANSPORTE DE MATERIAL DE LIMPEZA ATÉ 10 km | D36: m3 x km | E36: 205980.75 | H36: 1.44 | I36: =E36*H36 -> 296612.28 | J36: ACESSOS - LADO SANTOS E GUARUJÁ | K36: TERRAPLENAGEM | L36: 22.88.03.12.02
A37: 2.12 | C37: TRANSPORTE DE MATERIAL DE LIMPEZA ATÉ 15 km | D37: m3 x km | E37: 17088.75 | H37: 1.3 | I37: =E37*H37 -> 22215.375 | J37: ACESSOS - LADO SANTOS E GUARUJÁ | K37: TERRAPLENAGEM | L37: 22.88.03.12.03
A38: 2.13 | C38: TRANSPORTE DE MATERIAL DE LIMPEZA ALÉM DE 15 km | D38: m3 x km | E38: 87885 | H38: 1.12 | I38: =E38*H38 -> 98431.2 | J38: ACESSOS - LADO SANTOS E GUARUJÁ | K38: TERRAPLENAGEM | L38: 22.88.03.12.04
A39: 2.14 | C39: COMPACTAÇÃO DE ATERRO MAIOR/IGUAL 95% PN | D39: m3 | E39: 30672 | H39: 3.01 | I39: =E39*H39 -> 92322.72 | J39: ACESSOS - LADO SANTOS E GUARUJÁ | K39: TERRAPLENAGEM | L39: 22.04.01
A40: 3 | C40: =K40 -> PAVIMENTAÇÃO | J40: ACESSOS - LADO SANTOS E GUARUJÁ | K40: PAVIMENTAÇÃO | L40: 23
A41: 3.1 | C41: ESPALHAMENTO / REGULARIZAÇÃO / COMPACTAÇÃO DE MATERIAL EM BOTA-FORA. | D41: m3 | E41: 39829.93 | H41: 2.21 | I41: =E41*H41 -> 88024.145 | J41: ACESSOS - LADO SANTOS E GUARUJÁ | K41: PAVIMENTAÇÃO | L41: 22.02.09
A42: 3.2 | C42: MELHORIA / PREPARO SUB-LEITO -100% EN | D42: m2 | E42: 106846.37 | H42: 1.14 | I42: =E42*H42 -> 121804.86 | J42: ACESSOS - LADO SANTOS E GUARUJÁ | K42: PAVIMENTAÇÃO | L42: 22.02.09
A43: 3.3 | C43: SUB-BASE OU BASE BRITA GRADUADA SIMPLES | D43: m3 | E43: 21323.73 | H43: 168.38 | I43: =E43*H43 -> 3590489.7 | J43: ACESSOS - LADO SANTOS E GUARUJÁ | K43: PAVIMENTAÇÃO | L43: 23.04.03.01
A44: 3.4 | C44: SUB-BASE OU BASE DE PEDRA RACHÃO | D44: m3 | E44: 48590.87 | H44: 168.04 | I44: =E44*H44 -> 8165209.8 | J44: ACESSOS - LADO SANTOS E GUARUJÁ | K44: PAVIMENTAÇÃO | L44: 23.04.03.04
A45: 3.5 | C45: SUB-BASE OU BASE BRITA GRADUADA COM CIMENTO 4%VOL | D45: m3 | E45: 23047.05 | H45: 208.16 | I45: =E45*H45 -> 4797473.9 | J45: ACESSOS - LADO SANTOS E GUARUJÁ | K45: PAVIMENTAÇÃO | L45: 23.04.04.04
A46: 3.6 | C46: IMPRIMADURA BETUMINOSA IMPERMEABILIZANTE | D46: m2 | E46: 127597.58 | H46: 3.42 | I46: =E46*H46 -> 436383.72 | J46: ACESSOS - LADO SANTOS E GUARUJÁ | K46: PAVIMENTAÇÃO | L46: 23.05.01
A47: 3.7 | C47: IMPRIMADURA BETUMINOSA LIGANTE | D47: m2 | E47: 320347.81 | H47: 1.32 | I47: =E47*H47 -> 422859.11 | J47: ACESSOS - LADO SANTOS E GUARUJÁ | K47: PAVIMENTAÇÃO | L47: 23.05.02
A48: 3.8 | C48: IMPRIMADURA BETUMINOSA LIGANTE MODIFICADA COM POLÍMERO | D48: m2 | E48: 92170.2 | H48: 1.71 | I48: =E48*H48 -> 157611.04 | J48: ACESSOS - LADO SANTOS E GUARUJÁ | K48: PAVIMENTAÇÃO | L48: 23.05.04
A49: 3.9 | C49: CONCRETO ASFÁLTICO USINADO A QUENTE BINDER - GRADUAÇÃO B COM DOP | D49: m3 | E49: 10071.28 | H49: 488.89 | I49: =E49*H49 -> 4923748.1 | J49: ACESSOS - LADO SANTOS E GUARUJÁ | K49: PAVIMENTAÇÃO | L49: 23.08.02
A50: 3.10 | C50: CAMADA ROLAMENTO CBUQ - GRADUAÇÃO C - COM DOP | D50: m3 | E50: 7254.62 | H50: 526.62 | I50: =E50*H50 -> 3820428 | J50: ACESSOS - LADO SANTOS E GUARUJÁ | K50: PAVIMENTAÇÃO | L50: 23.08.03.03
A51: 3.11 | C51: CONCRETO ASFÁLTICO MODIFICADO POR POLÍMERO | D51: m3 | E51: 4343.57 | H51: 637.36 | I51: =E51*H51 -> 2768417.8 | J51: ACESSOS - LADO SANTOS E GUARUJÁ | K51: PAVIMENTAÇÃO | L51: 23.08.05
A52: 3.12 | C52: FRESAGEM CONTÍNUA DE PAVIMENTO, INDEPENDENTE DA ESPESSURA | D52: m3 | E52: 4776.51 | H52: 139.28 | I52: =E52*H52 -> 665272.31 | J52: ACESSOS - LADO SANTOS E GUARUJÁ | K52: PAVIMENTAÇÃO | L52: 23.10.01
A53: 4 | C53: =K53 -> OBRAS DE ARTE CORRENTE E DRENAGEM | J53: ACESSOS - LADO SANTOS E GUARUJÁ | K53: OBRAS DE ARTE CORRENTE E DRENAGEM | L53: 24
A54: 4.1 | C54: ESPALHAMENTO / REGULARIZAÇÃO / COMPACTAÇÃO DE MATERIAL EM BOTA-FORA. | D54: m3 | E54: 25813.9 | H54: 2.21 | I54: =E54*H54 -> 57048.719 | J54: ACESSOS - LADO SANTOS E GUARUJÁ | K54: OBRAS DE ARTE CORRENTE E DRENAGEM | L54: 22.02.09
A55: 4.2 | C55: TRANSPORTE DE MATERIAL DE 1ª/2ª CATEGORIA ATÉ 5 km | D55: m3 x km | E55: 129069.46 | H55: 1.71 | I55: =E55*H55 -> 220708.78 | J55: ACESSOS - LADO SANTOS E GUARUJÁ | K55: OBRAS DE ARTE CORRENTE E DRENAGEM | L55: 22.03.03
A56: 4.3 | C56: ESCAVAÇÃO MECÂNICA PARA OBRAS SEM EXPLOSIVO | D56: m3 | E56: 15021.05 | H56: 10.92 | I56: =E56*H56 -> 164029.87 | J56: ACESSOS - LADO SANTOS E GUARUJÁ | K56: OBRAS DE ARTE CORRENTE E DRENAGEM | L56: 24.02.02
A57: 4.4 | C57: ESCAVAÇÃO DE DRENOS E BUEIROS SEM EXPLOSIVO | D57: m3 | E57: 121417.43 | H57: 62.83 | I57: =E57*H57 -> 7628657.1 | J57: ACESSOS - LADO SANTOS E GUARUJÁ | K57: OBRAS DE ARTE CORRENTE E DRENAGEM | L57: 24.02.08
A58: 4.5 | C58: ESCORAMENTO DE VALAS/CAVAS -CONTÍNUO | D58: m2 | E58: 23510.93 | H58: 96 | I58: =E58*H58 -> 2257049.3 | J58: ACESSOS - LADO SANTOS E GUARUJÁ | K58: OBRAS DE ARTE CORRENTE E DRENAGEM | L58: 24.03.06
A59: 4.6 | C59: ESCORAMENTO DE VALAS/CAVAS -DESCONTÍNUO | D59: m2 | E59: 110292.14 | H59: 64.68 | I59: =E59*H59 -> 7133695.6 | J59: ACESSOS - LADO SANTOS E GUARUJÁ | K59: OBRAS DE ARTE CORRENTE E DRENAGEM | L59: 24.03.07
A60: 4.7 | C60: FORMA PLANA PARA CONCRETO COMUM | D60: m2 | E60: 8338.55 | H60: 80.07 | I60: =E60*H60 -> 667667.7 | J60: ACESSOS - LADO SANTOS E GUARUJÁ | K60: OBRAS DE ARTE CORRENTE E DRENAGEM | L60: 24.05.01
A61: 4.8 | C61: BARRA DE AÇO CA-50 | D61: kg | E61: 270419.44 | H61: 8.52 | I61: =E61*H61 -> 2303973.6 | J61: ACESSOS - LADO SANTOS E GUARUJÁ | K61: OBRAS DE ARTE CORRENTE E DRENAGEM | L61: 24.06.02
A62: 4.9 | C62: CONCRETO fck 10 MPa | D62: m3 | E62: 453.61 | H62: 386.3 | I62: =E62*H62 -> 175229.54 | J62: ACESSOS - LADO SANTOS E GUARUJÁ | K62: OBRAS DE ARTE CORRENTE E DRENAGEM | L62: 24.07.01
A63: 4.10 | C63: CONCRETO fck 15 MPa | D63: m3 | E63: 1241.07 | H63: 426.19 | I63: =E63*H63 -> 528931.62 | J63: ACESSOS - LADO SANTOS E GUARUJÁ | K63: OBRAS DE ARTE CORRENTE E DRENAGEM | L63: 24.07.02
A64: 4.11 | C64: CONCRETO fck 20 MPa | D64: m3 | E64: 1248.84 | H64: 455.28 | I64: =E64*H64 -> 568571.88 | J64: ACESSOS - LADO SANTOS E GUARUJÁ | K64: OBRAS DE ARTE CORRENTE E DRENAGEM | L64: 24.07.04
A65: 4.12 | C65: CONCRETO fck 25 MPa | D65: m3 | E65: 1049.76 | H65: 467.63 | I65: =E65*H65 -> 490899.27 | J65: ACESSOS - LADO SANTOS E GUARUJÁ | K65: OBRAS DE ARTE CORRENTE E DRENAGEM | L65: 24.07.05
... A87: 4.34 | C87: LAJOTA PRÉ MOLDADA DE CONCRETO E=7CM JUNTA DE GRAMA | D87: m2 | E87: 10386 | H87: 55.24 | I87: =E87*H87 -> 573722.64 | J87: ACESSOS - LADO SANTOS E GUARUJÁ | K87: OBRAS DE ARTE CORRENTE E DRENAGEM | L87: 24.88.17.02.15
A88: 5 | C88: =K88 -> OBRAS DE CONTENÇÃO GEOTÉCNICA | J88: ACESSOS - LADO SANTOS E GUARUJÁ | K88: OBRAS DE CONTENÇÃO GEOTÉCNICA | L88: 25
A89: 5.1 | C89: DEMOLIÇÃO DE GUIA EM CONCRETO ARMADO -PAREDE DIAFRAGMA | D89: m3 | E89: 1562.9 | H89: 294.37 | I89: =E89*H89 -> 460070.87 | J89: ACESSOS - LADO SANTOS E GUARUJÁ | K89: OBRAS DE CONTENÇÃO GEOTÉCNICA | L89: 25.21.88.05.01
A90: 5.2 | C90: ESCAVAÇÃO E CARGA DE MATERIAL DE 1ª/2ª CATEGORIA | D90: m3 | E90: 199090 | H90: 4.9 | I90: =E90*H90 -> 975541 | J90: ACESSOS - LADO SANTOS E GUARUJÁ | K90: OBRAS DE CONTENÇÃO GEOTÉCNICA | L90: 22.02.01
A91: 5.3 | C91: ESCAVAÇÃO E CARGA DE SOLO MOLE SOB LÂMINA D' ÁGUA | D91: m3 | E91: 90000 | H91: 10.66 | I91: =E91*H91 -> 959400 | J91: ACESSOS - LADO SANTOS E GUARUJÁ | K91: OBRAS DE CONTENÇÃO GEOTÉCNICA | L91: 22.02.05
A92: 5.4 | C92: ESPALHAMENTO / REGULARIZAÇÃO / COMPACTAÇÃO DE MATERIAL EM BOTA-FORA. | D92: m3 | E92: 268240 | H92: 2.21 | I92: =E92*H92 -> 592810.4 | J92: ACESSOS - LADO SANTOS E GUARUJÁ | K92: OBRAS DE CONTENÇÃO GEOTÉCNICA | L92: 22.02.09
A93: 5.5 | C93: TRANSPORTE DE MATERIAL DE 1ª/2ª CATEGORIA ATÉ 15 km | D93: m3 x km | E93: 2836200 | H93: 1.26 | I93: =E93*H93 -> 3573612 | J93: ACESSOS - LADO SANTOS E GUARUJÁ | K93: OBRAS DE CONTENÇÃO GEOTÉCNICA | L93: 22.03.05
A94: 5.6 | C94: TRANSPORTE DE MATERIAL DE 1ª/2ª CATEGORIA ALÉM DE 15 km | D94: m3 x km | E94: 7129600 | H94: 0.99 | I94: =E94*H94 -> 7058304 | J94: ACESSOS - LADO SANTOS E GUARUJÁ | K94: OBRAS DE CONTENÇÃO GEOTÉCNICA | L94: 22.03.06
A95: 5.7 | C95: TRANSPORTE DE SOLO MOLE ALÉM DE 2 km | D95: m3 x km | E95: 4394542.1 | H95: 2.41 | I95: =E95*H95 -> 10590846 | J95: ACESSOS - LADO SANTOS E GUARUJÁ | K95: OBRAS DE CONTENÇÃO GEOTÉCNICA | L95: 22.03.10
A96: 5.8 | C96: COMPACTAÇÃO DE ATERRO MAIOR/IGUAL 95% PN | D96: m3 | E96: 189080 | H96: 3.01 | I96: =E96*H96 -> 569130.8 | J96: ACESSOS - LADO SANTOS E GUARUJÁ | K96: OBRAS DE CONTENÇÃO GEOTÉCNICA | L96: 22.04.01
A97: 5.9 | C97: FUNDAÇÃO DE ATERRO COM PEDRA RACHÃO | D97: m3 | E97: 24396 | H97: 101.3 | I97: =E97*H97 -> 2471314.8 | J97: ACESSOS - LADO SANTOS E GUARUJÁ | K97: OBRAS DE CONTENÇÃO GEOTÉCNICA | L97: 22.06.04
A98: 5.10 | C98: VOLUME DE ATERRO COMPACTADO | D98: m3 | E98: 25662.52 | H98: 8.52 | I98: =E98*H98 -> 218644.67 | J98: ACESSOS - LADO SANTOS E GUARUJÁ | K98: OBRAS DE CONTENÇÃO GEOTÉCNICA | L98: 24.01.01
A99: 5.11 | C99: ENCHIMENTO DE VALA COM AREIA LAVADA | D99: m3 | E99: 1100 | H99: 131.19 | I99: =E99*H99 -> 144309 | J99: ACESSOS - LADO SANTOS E GUARUJÁ | K99: OBRAS DE CONTENÇÃO GEOTÉCNICA | L99: 24.12.02
A100: 5.12 | C100: MANTA GEOTEXTIL NÃO TECIDA RESISTENCIA LONGITUDIANAL 31 kN/m | D100: m2 | E100: 40660 | H100: 16.95 | I100: =E100*H100 -> 689187 | J100: ACESSOS - LADO SANTOS E GUARUJÁ | K100: OBRAS DE CONTENÇÃO GEOTÉCNICA | L100: 24.14.01.09
... A123: 5.35 | C123: FORNECIMENTO DE PERFIL METÁLICO CS-350 MASSA LINEAR DE 144 kg/m -EXECUÇÃO DE ESTRONCAS | D123: kg | E123: 203812.21 | H123: 10.76 | I123: =E123*H123 -> 2193019.4 | J123: ACESSOS - LADO SANTOS E GUARUJÁ | K123: OBRAS DE CONTENÇÃO GEOTÉCNICA | L123: 29.88.07.08
A124: 6 | C124: =K124 -> OBRAS DE ARTE ESPECIAIS | J124: ACESSOS - LADO SANTOS E GUARUJÁ | K124: OBRAS DE ARTE ESPECIAIS | L124: 26
A125: 6.1 | C125: ESCAVAÇÃO E CARGA DE SOLO MOLE SOB LÂMINA D' ÁGUA | D125: m3 | E125: 9836 | H125: 10.66 | I125: =E125*H125 -> 104851.76 | J125: ACESSOS - LADO SANTOS E GUARUJÁ | K125: OBRAS DE ARTE ESPECIAIS | L125: 22.02.05
A126: 6.2 | C126: COMPACTAÇÃO MANUAL COM REATERRO SOLO LOCAL | D126: m3 | E126: 2067 | H126: 24.16 | I126: =E126*H126 -> 49938.72 | J126: ACESSOS - LADO SANTOS E GUARUJÁ | K126: OBRAS DE ARTE ESPECIAIS | L126: 24.12.08
A127: 6.3 | C127: SOLO REFORÇADO TIPO GREIDE COM ALTURA DE 0 A 6 METROS | D127: m2 | E127: 19520 | H127: 716.86 | I127: =E127*H127 -> 13993107 | J127: ACESSOS - LADO SANTOS E GUARUJÁ | K127: OBRAS DE ARTE ESPECIAIS | L127: 25.20.01
A128: 6.4 | C128: FORNECIMENTO E CRAVAÇÃO DE COMBINED WALL WITH TUBULAR PILES COM COMPRIMENTO ATÉ 50,0 METROS, EM AÇO CARBONO COM RESISTÊNCIA CARACTERISTICA SUPERIOR A 350 Mpa, INCLUSIVE JUNTA SELANTE POLIMÉRICA ENTRE ELEMENTOS | D128: kg | E128: 311987.7 | H128: 10.89 | I128: =E128*H128 -> 3397546.1 | J128: ACESSOS - LADO SANTOS E GUARUJÁ | K128: OBRAS DE ARTE ESPECIAIS | L128: 25.88.04.06.02
A129: 6.5 | C129: ESCAVAÇÃO MANUAL PARA OBRAS SEM EXPLOSIVO | D129: m3 | E129: 5795 | H129: 50.17 | I129: =E129*H129 -> 290735.15 | J129: ACESSOS - LADO SANTOS E GUARUJÁ | K129: OBRAS DE ARTE ESPECIAIS | L129: 26.01.01
A130: 6.6 | C130: ESTACA CONCRETO PRÉ-MOLDADO -70/80 T | D130: m | E130: 1120 | H130: 185.58 | I130: =E130*H130 -> 207849.6 | J130: ACESSOS - LADO SANTOS E GUARUJÁ | K130: OBRAS DE ARTE ESPECIAIS | L130: 26.02.05
A131: 6.7 | C131: ESTACÃO EM SOLO D = 1,20M | D131: m | E131: 320 | H131: 1808.32 | I131: =E131*H131 -> 578662.4 | J131: ACESSOS - LADO SANTOS E GUARUJÁ | K131: OBRAS DE ARTE ESPECIAIS | L131: 26.02.14
A132: 6.8 | C132: ESTACÃO EM SOLO D = 1,40M | D132: m | E132: 1216 | H132: 2361.98 | I132: =E132*H132 -> 2872167.7 | J132: ACESSOS - LADO SANTOS E GUARUJÁ | K132: OBRAS DE ARTE ESPECIAIS | L132: 26.02.15
A133: 6.9 | C133: ESTACÃO EM SOLO D = 1,80M | D133: m | E133: 1728 | H133: 3766.11 | I133: =E133*H133 -> 6507838.1 | J133: ACESSOS - LADO SANTOS E GUARUJÁ | K133: OBRAS DE ARTE ESPECIAIS | L133: 26.02.18
A134: 6.10 | C134: CIMBRAMENTO METALICO PARA PONTES E VIADUTOS | D134: m3 | E134: 68659 | H134: 56.65 | I134: =E134*H134 -> 3889532.4 | J134: ACESSOS - LADO SANTOS E GUARUJÁ | K134: OBRAS DE ARTE ESPECIAIS | L134: 26.04.04
A135: 6.11 | C135: ANDAIME TUBULAR | D135: m3 | E135: 950 | H135: 18.12 | I135: =E135*H135 -> 17214 | J135: ACESSOS - LADO SANTOS E GUARUJÁ | K135: OBRAS DE ARTE ESPECIAIS | L135: 26.04.06
A136: 6.12 | C136: FORMA PLANA PARA CONCRETO COMUM | D136: m2 | E136: 23169.08 | H136: 80.07 | I136: =E136*H136 -> 1855148.2 | J136: ACESSOS - LADO SANTOS E GUARUJÁ | K136: OBRAS DE ARTE ESPECIAIS | L136: 26.05.01
... A163: 6.39 | C163: MERGULHADORES DE INSPEÇÃO -EQUIPE COMPOSTA POR 4 MERGULHADORES, 2 SUBMERSOS E 2 EM TERRA | D163: h | E163: 1320 | H163: 675 | I163: =E163*H163 -> 891000 | J163: ACESSOS - LADO SANTOS E GUARUJÁ | K163: OBRAS DE ARTE ESPECIAIS | L163: 29.88.23.02
A164: 7 | C164: =K164 -> SINALIZAÇÃO E ELEMENTOS DE SEGURANÇA | J164: ACESSOS - LADO SANTOS E GUARUJÁ | K164: SINALIZAÇÃO E ELEMENTOS DE SEGURANÇA | L164: 28
A165: 7.1 | C165: POSTE COMPOSTO PARA SINALIZAÇÃO | D165: unid | E165: 6 | H165: 3807 | I165: =E165*H165 -> 22842 | J165: ACESSOS - LADO SANTOS E GUARUJÁ | K165: SINALIZAÇÃO E ELEMENTOS DE SEGURANÇA | L165: 28.88.70.05
A166: 7.2 | C166: BPC -BRAÇO PROJETADO EM COLUNA (SINALIZAÇÃO VERTICAL) -PP DA CET-SP - A2-191-DSV3 -COLUNA E BRAÇO 5x5,25 | D166: unid | E166: 9 | H166: 3132 | I166: =E166*H166 -> 28188 | J166: ACESSOS - LADO SANTOS E GUARUJÁ | K166: SINALIZAÇÃO E ELEMENTOS DE SEGURANÇA | L166: 28.88.70.01
A167: 7.3 | C167: BRAÇO PROJETADO (SINALIZAÇÃO SEMAFÓRICA) -PP'S DA CET - CET-21, CET-22, CET-28, CET-28 e CET-36 . | D167: unid | E167: 10 | H167: 2862 | I167: =E167*H167 -> 28620 | J167: ACESSOS - LADO SANTOS E GUARUJÁ | K167: SINALIZAÇÃO E ELEMENTOS DE SEGURANÇA | L167: 28.88.70.03
A168: 7.4 | C168: POSTE SIMPLES PARA SINALIZAÇÃO, DE ACORDO COM A CET-22 | D168: unid | E168: 16 | H168: 3483 | I168: =E168*H168 -> 55728 | J168: ACESSOS - LADO SANTOS E GUARUJÁ | K168: SINALIZAÇÃO E ELEMENTOS DE SEGURANÇA | L168: 28.88.70.04
A169: 7.5 | C169: FOCO SEMAFÓRICO PP'S GCR-1057-CONJUNTO 200 CONV. BP E GCR-1056-CONJUNTO 200 CONV. CS | D169: unid | E169: 34 | H169: 3267 | I169: =E169*H169 -> 111078 | J169: ACESSOS - LADO SANTOS E GUARUJÁ | K169: SINALIZAÇÃO E ELEMENTOS DE SEGURANÇA | L169: 28.88.70.02
A170: 7.6 | C170: SUPORTE DE PLACAS DE SOLO ECOLÓGICO E COLAPSIVEL 75X75 mm | D170: m | E170: 64 | H170: 80.24 | I170: =E170*H170 -> 5135.36 | J170: ACESSOS - LADO SANTOS E GUARUJÁ | K170: SINALIZAÇÃO E ELEMENTOS DE SEGURANÇA | L170: 28.06.30
A171: 7.7 | C171: FORNECIMENTO, TRANSPORTE E FIXAÇÃO DE SEMI-PÓRTICO TUBULAR EM BALANCO VÃO DE 5,10 m | D171: unid | E171: 76 | H171: 17001.17 | I171: =E171*H171 -> 1292088.9 | J171: ACESSOS - LADO SANTOS E GUARUJÁ | K171: SINALIZAÇÃO E ELEMENTOS DE SEGURANÇA | L171: 28.02.04.01
...

Sheet Original
B1: ID Primario | C1: ID | E1: SETOR | F1: GRUPO | G1: ITEM | H1: UNIDADE | I1: QUANT. | J1: PREÇO UNITÁRIO | K1: PREÇO TOTAL
B2: 1 | C2: 1 | D2: 21 | E2: ACESSOS - LADO SANTOS E GUARUJÁ | F2: SERVIÇOS PRELIMINARES
B3: 2 | C3: 1.1 | D3: 21.03.01 | E3: ACESSOS - LADO SANTOS E GUARUJÁ | F3: SERVIÇOS PRELIMINARES | G3: REMOÇÃO CERCA ARAME, INCLUSIVE TRANSPORTE | H3: m | I3: 400 | J3: 12.03 | K3: =I3*J3 -> 4812
B4: 3 | C4: 1.2 | D4: 21.03.02 | E4: ACESSOS - LADO SANTOS E GUARUJÁ | F4: SERVIÇOS PRELIMINARES | G4: REMOCAO DE DEFENSA METALICA SIMPLES | H4: m | I4: 200 | J4: 43.91 | K4: =I4*J4 -> 8782
B5: 4 | C5: 1.3 | D5: 21.03.08 | E5: ACESSOS - LADO SANTOS E GUARUJÁ | F5: SERVIÇOS PRELIMINARES | G5: REMOÇÃO E TRANSPORTE DE GUIA PRÉ-MOLDADA | H5: m | I5: 18670.46 | J5: 17.64 | K5: =I5*J5 -> 329346.91
B6: 5 | C6: 1.4 | D6: 21.88.0.,01 | E6: ACESSOS - LADO SANTOS E GUARUJÁ | F6: SERVIÇOS PRELIMINARES | G6: DEMOLIÇÃO DE CONCRETO ARMADO | H6: m3 | I6: 39039.41 | J6: 294.37 | K6: =I6*J6 -> 11492031
B7: 6 | C7: 1.5 | D7: 21.88.05.02 | E7: ACESSOS - LADO SANTOS E GUARUJÁ | F7: SERVIÇOS PRELIMINARES | G7: DEMOLIÇÃO DE CONCRETO SIMPLES | H7: m3 | I7: 63709.51 | J7: 154.29 | K7: =(I7*J7)-0.008 -> 9829740.3
B8: 7 | C8: 1.6 | D8: 21.88.05.05 | E8: ACESSOS - LADO SANTOS E GUARUJÁ | F8: SERVIÇOS PRELIMINARES | G8: DEMOLIÇÃO DE EDIFICAÇÃO EM ALVENARIA | H8: m2 | I8: 66412.68 | J8: 35.6 | K8: =I8*J8 -> 2364291.4
B9: 8 | C9: 1.7 | D9: 21.88.05.06 | E9: ACESSOS - LADO SANTOS E GUARUJÁ | F9: SERVIÇOS PRELIMINARES | G9: DEMOLIÇÃO DE EDIFICAÇÃO EM MADEIRA | H9: m2 | I9: 34516.27 | J9: 13.19 | K9: =I9*J9 -> 455269.6
B10: 9 | C10: 1.8 | D10: 21.88.05.07 | E10: ACESSOS - LADO SANTOS E GUARUJÁ | F10: SERVIÇOS PRELIMINARES | G10: DEMOLIÇÃO DE PAVIMENTO FLEXIVEL | H10: m3 | I10: 41618.81 | J10: 18.52 | K10: =I10*J10 -> 770780.36
B11: 10 | C11: 1.9 | D11: 21.88.19.01 | E11: ACESSOS - LADO SANTOS E GUARUJÁ | F11: SERVIÇOS PRELIMINARES | G11: MURO DE FECHAMENTO COM PLACAS E MOURÕES PRÉ-MOLDADO H=2,00 m | H11: m | I11: 100 | J11: 125.96 | K11: =I11*J11 -> 12596
B12: 11 | C12: 1.10 | D12: 21.88.19.08.03 | E12: ACESSOS - LADO SANTOS E GUARUJÁ | F12: SERVIÇOS PRELIMINARES | G12: TRANSPORTE DE MATERIAL CLASSE IIA e IIB PARA BOTA-FORA ESPECIAL | H12: ton x km | I12: 7813575.8 | J12: 1.24 | K12: =I12*J12 -> 9688834
B13: 12 | C13: 1.11 | D13: 21.88.20.01 | E13: ACESSOS - LADO SANTOS E GUARUJÁ | F13: SERVIÇOS PRELIMINARES | G13: BRITAGEM DE MATERIAL DE DEMOLIÇÃO | H13: m3 | I13: 101234.38 | J13: 50.86 | K13: =I13*J13 -> 5148780.6
B14: 13 | C14: 1.12 | D14: 21.88.21.02 | E14: ACESSOS - LADO SANTOS E GUARUJÁ | F14: SERVIÇOS PRELIMINARES | G14: DEPOSIÇÃO DE MATERIAL CLASSE IIA, EM BOTA-FORA ESPECIAL | H14: ton | I14: 151405.85 | J14: 94.5 | K14: =I14*J14 -> 14307853
B15: 14 | C15: 1.13 | D15: 21.88.21.03 | E15: ACESSOS - LADO SANTOS E GUARUJÁ | F15: SERVIÇOS PRELIMINARES | G15: DEPOSIÇÃO DE MATERIAL CLASSE IIB, EM BOTA-FORA ESPECIAL | H15: ton | I15: 151401.71 | J15: 67.5 | K15: =I15*J15 -> 10219615
B16: 15 | C16: 1.14 | D16: 22.88.03.03 | E16: ACESSOS - LADO SANTOS E GUARUJÁ | F16: SERVIÇOS PRELIMINARES | G16: TRANSPORTE DE MATERIAL DE DEMOLIÇÃO ATÉ 5 KM | H16: m3 x km | I16: 506171.91 | J16: 1.71 | K16: =I16*J16 -> 865553.97
B17: 16 | C17: 2 | D17: 22 | E17: ACESSOS - LADO SANTOS E GUARUJÁ | F17: TERRAPLENAGEM
B18: 17 | C18: 2.1 | D18: 22.01.01 | E18: ACESSOS - LADO SANTOS E GUARUJÁ | F18: TERRAPLENAGEM | G18: LIMPEZA ÁRVORES DE TERRENO SEM DESTOCAMENTO DE ÁRVORES | H18: m2 | I18: 181263 | J18: 0.28 | K18: =I18*J18 -> 50753.64
B19: 18 | C19: 2.2 | D19: 22.02.01 | E19: ACESSOS - LADO SANTOS E GUARUJÁ | F19: TERRAPLENAGEM | G19: ESCAVAÇÃO E CARGA DE MATERIAL DE 1ª/2ª CATEGORIA | H19: m3 | I19: 49049.95 | J19: 4.9 | K19: =I19*J19 -> 240344.76
B20: 19 | C20: 2.3 | D20: 22.02.02 | E20: ACESSOS - LADO SANTOS E GUARUJÁ | F20: TERRAPLENAGEM | G20: ESCAVAÇÃO E CARGA DE MATERIAL DE 2ª CATEGORIA COM RIPPER | H20: m3 | I20: 691.55 | J20: 5.44 | K20: =I20*J20 -> 3762.032
B21: 20 | C21: 2.4 | D21: 22.02.06 | E21: ACESSOS - LADO SANTOS E GUARUJÁ | F21: TERRAPLENAGEM | G21: CARGA DE MATERIAL DE LIMPEZA | H21: m3 | I21: 36252.6 | J21: 2.26 | K21: =I21*J21 -> 81930.876
B22: 21 | C22: 2.5 | D22: 22.03.01 | E22: ACESSOS - LADO SANTOS E GUARUJÁ | F22: TERRAPLENAGEM | G22: TRANSPORTE DE MATERIAL DE 1ª/2ª CATEGORIA ATÉ 1 km | H22: m3 x km | I22: 729.26 | J22: 3.74 | K22: =I22*J22 -> 2727.4324
B23: 22 | C23: 2.6 | D23: 22.03.02 | E23: ACESSOS - LADO SANTOS E GUARUJÁ | F23: TERRAPLENAGEM | G23: TRANSPORTE DE MATERIAL DE 1ª/2ª CATEGORIA ATÉ 2 km | H23: m3 x km | I23: 2187.76 | J23: 2.2 | K23: =I23*J23 -> 4813.072
B24: 23 | C24: 2.7 | D24: 22.03.03 | E24: ACESSOS - LADO SANTOS E GUARUJÁ | F24: TERRAPLENAGEM | G24: TRANSPORTE DE MATERIAL DE 1ª/2ª CATEGORIA ATÉ 5 km | H24: m3 x km | I24: 3000.93 | J24: 1.71 | K24: =I24*J24 -> 5131.5903
B25: 24 | C25: 2.8 | D25: 22.03.04 | E25: ACESSOS - LADO SANTOS E GUARUJÁ | F25: TERRAPLENAGEM | G25: TRANSPORTE DE MATERIAL DE 1ª/2ª CATEGORIA ATÉ 10 km | H25: m3 x km | I25: 247956.53 | J25: 1.43 | K25: =I25*J25 -> 354577.84
B26: 25 | C26: 2.9 | D26: 22.03.05 | E26: ACESSOS - LADO SANTOS E GUARUJÁ | F26: TERRAPLENAGEM | G26: TRANSPORTE DE MATERIAL DE 1ª/2ª CATEGORIA ATÉ 15 km | H26: m3 x km | I26: 63019.43 | J26: 1.26 | K26: =I26*J26 -> 79404.482
B27: 26 | C27: 2.10 | D27: 22.88.03.12.01 | E27: ACESSOS - LADO SANTOS E GUARUJÁ | F27: TERRAPLENAGEM | G27: TRANSPORTE DE MATERIAL DE LIMPEZA ATÉ 5 km | H27: m3 x km | I27: 35550.75 | J27: 1.93 | K27: =I27*J27 -> 68612.947
B28: 27 | C28: 2.11 | D28: 22.88.03.12.02 | E28: ACESSOS - LADO SANTOS E GUARUJÁ | F28: TERRAPLENAGEM | G28: TRANSPORTE DE MATERIAL DE LIMPEZA ATÉ 10 km | H28: m3 x km | I28: 205980.75 | J28: 1.44 | K28: =I28*J28 -> 296612.28
B29: 28 | C29: 2.12 | D29: 22.88.03.12.03 | E29: ACESSOS - LADO SANTOS E GUARUJÁ | F29: TERRAPLENAGEM | G29: TRANSPORTE DE MATERIAL DE LIMPEZA ATÉ 15 km | H29: m3 x km | I29: 17088.75 | J29: 1.3 | K29: =I29*J29 -> 22215.375
... B31: 30 | C31: 2.14 | D31: 22.04.01 | E31: ACESSOS - LADO SANTOS E GUARUJÁ | F31: TERRAPLENAGEM | G31: COMPACTAÇÃO DE ATERRO MAIOR/IGUAL 95% PN | H31: m3 | I31: 30672 | J31: 3.01 | K31: =I31*J31 -> 92322.72
B32: 31 | C32: 3 | D32: 23 | E32: ACESSOS - LADO SANTOS E GUARUJÁ | F32: PAVIMENTAÇÃO
B33: 32 | C33: 3.1 | D33: 22.02.09 | E33: ACESSOS - LADO SANTOS E GUARUJÁ | F33: PAVIMENTAÇÃO | G33: ESPALHAMENTO / REGULARIZAÇÃO / COMPACTAÇÃO DE MATERIAL EM BOTA-FORA. | H33: m3 | I33: 39829.93 | J33: 2.21 | K33: =I33*J33 -> 88024.145
B34: 33 | C34: 3.2 | D34: 22.02.09 | E34: ACESSOS - LADO SANTOS E GUARUJÁ | F34: PAVIMENTAÇÃO | G34: MELHORIA / PREPARO SUB-LEITO -100% EN | H34: m2 | I34: 106846.37 | J34: 1.14 | K34: =I34*J34 -> 121804.86
B35: 34 | C35: 3.3 | D35: 23.04.03.01 | E35: ACESSOS - LADO SANTOS E GUARUJÁ | F35: PAVIMENTAÇÃO | G35: SUB-BASE OU BASE BRITA GRADUADA SIMPLES | H35: m3 | I35: 21323.73 | J35: 168.38 | K35: =I35*J35 -> 3590489.7
B36: 35 | C36: 3.4 | D36: 23.04.03.04 | E36: ACESSOS - LADO SANTOS E GUARUJÁ | F36: PAVIMENTAÇÃO | G36: SUB-BASE OU BASE DE PEDRA RACHÃO | H36: m3 | I36: 48590.87 | J36: 168.04 | K36: =I36*J36 -> 8165209.8
B37: 36 | C37: 3.5 | D37: 23.04.04.04 | E37: ACESSOS - LADO SANTOS E GUARUJÁ | F37: PAVIMENTAÇÃO | G37: SUB-BASE OU BASE BRITA GRADUADA COM CIMENTO 4%VOL | H37: m3 | I37: 23047.05 | J37: 208.16 | K37: =I37*J37 -> 4797473.9
B38: 37 | C38: 3.6 | D38: 23.05.01 | E38: ACESSOS - LADO SANTOS E GUARUJÁ | F38: PAVIMENTAÇÃO | G38: IMPRIMADURA BETUMINOSA IMPERMEABILIZANTE | H38: m2 | I38: 127597.58 | J38: 3.42 | K38: =I38*J38 -> 436383.72
B39: 38 | C39: 3.7 | D39: 23.05.02 | E39: ACESSOS - LADO SANTOS E GUARUJÁ | F39: PAVIMENTAÇÃO | G39: IMPRIMADURA BETUMINOSA LIGANTE | H39: m2 | I39: 320347.81 | J39: 1.32 | K39: =I39*J39 -> 422859.11
B40: 39 | C40: 3.8 | D40: 23.05.04 | E40: ACESSOS - LADO SANTOS E GUARUJÁ | F40: PAVIMENTAÇÃO | G40: IMPRIMADURA BETUMINOSA LIGANTE MODIFICADA COM POLÍMERO | H40: m2 | I40: 92170.2 | J40: 1.71 | K40: =I40*J40 -> 157611.04
B41: 40 | C41: 3.9 | D41: 23.08.02 | E41: ACESSOS - LADO SANTOS E GUARUJÁ | F41: PAVIMENTAÇÃO | G41: CONCRETO ASFÁLTICO USINADO A QUENTE BINDER - GRADUAÇÃO B COM DOP | H41: m3 | I41: 10071.28 | J41: 488.89 | K41: =I41*J41 -> 4923748.1
B42: 41 | C42: 3.10 | D42: 23.08.03.03 | E42: ACESSOS - LADO SANTOS E GUARUJÁ | F42: PAVIMENTAÇÃO | G42: CAMADA ROLAMENTO CBUQ - GRADUAÇÃO C - COM DOP | H42: m3 | I42: 7254.62 | J42: 526.62 | K42: =I42*J42 -> 3820428
B43: 42 | C43: 3.11 | D43: 23.08.05 | E43: ACESSOS - LADO SANTOS E GUARUJÁ | F43: PAVIMENTAÇÃO | G43: CONCRETO ASFÁLTICO MODIFICADO POR POLÍMERO | H43: m3 | I43: 4343.57 | J43: 637.36 | K43: =I43*J43 -> 2768417.8
B44: 43 | C44: 3.12 | D44: 23.10.01 | E44: ACESSOS - LADO SANTOS E GUARUJÁ | F44: PAVIMENTAÇÃO | G44: FRESAGEM CONTÍNUA DE PAVIMENTO, INDEPENDENTE DA ESPESSURA | H44: m3 | I44: 4776.51 | J44: 139.28 | K44: =I44*J44 -> 665272.31
B45: 44 | C45: 4 | D45: 24 | E45: ACESSOS - LADO SANTOS E GUARUJÁ | F45: OBRAS DE ARTE CORRENTE E DRENAGEM
B46: 45 | C46: 4.1 | D46: 22.02.09 | E46: ACESSOS - LADO SANTOS E GUARUJÁ | F46: OBRAS DE ARTE CORRENTE E DRENAGEM | G46: ESPALHAMENTO / REGULARIZAÇÃO / COMPACTAÇÃO DE MATERIAL EM BOTA-FORA. | H46: m3 | I46: 25813.9 | J46: 2.21 | K46: =I46*J46 -> 57048.719
B47: 46 | C47: 4.2 | D47: 22.03.03 | E47: ACESSOS - LADO SANTOS E GUARUJÁ | F47: OBRAS DE ARTE CORRENTE E DRENAGEM | G47: TRANSPORTE DE MATERIAL DE 1ª/2ª CATEGORIA ATÉ 5 km | H47: m3 x km | I47: 129069.46 | J47: 1.71 | K47: =I47*J47 -> 220708.78
B48: 47 | C48: 4.3 | D48: 24.02.02 | E48: ACESSOS - LADO SANTOS E GUARUJÁ | F48: OBRAS DE ARTE CORRENTE E DRENAGEM | G48: ESCAVAÇÃO MECÂNICA PARA OBRAS SEM EXPLOSIVO | H48: m3 | I48: 15021.05 | J48: 10.92 | K48: =I48*J48 -> 164029.87
B49: 48 | C49: 4.4 | D49: 24.02.08 | E49: ACESSOS - LADO SANTOS E GUARUJÁ | F49: OBRAS DE ARTE CORRENTE E DRENAGEM | G49: ESCAVAÇÃO DE DRENOS E BUEIROS SEM EXPLOSIVO | H49: m3 | I49: 121417.43 | J49: 62.83 | K49: =I49*J49 -> 7628657.1
B50: 49 | C50: 4.5 | D50: 24.03.06 | E50: ACESSOS - LADO SANTOS E GUARUJÁ | F50: OBRAS DE ARTE CORRENTE E DRENAGEM | G50: ESCORAMENTO DE VALAS/CAVAS -CONTÍNUO | H50: m2 | I50: 23510.93 | J50: 96 | K50: =I50*J50 -> 2257049.3
B51: 50 | C51: 4.6 | D51: 24.03.07 | E51: ACESSOS - LADO SANTOS E GUARUJÁ | F51: OBRAS DE ARTE CORRENTE E DRENAGEM | G51: ESCORAMENTO DE VALAS/CAVAS -DESCONTÍNUO | H51: m2 | I51: 110292.14 | J51: 64.68 | K51: =I51*J51 -> 7133695.6
B52: 51 | C52: 4.7 | D52: 24.05.01 | E52: ACESSOS - LADO SANTOS E GUARUJÁ | F52: OBRAS DE ARTE CORRENTE E DRENAGEM | G52: FORMA PLANA PARA CONCRETO COMUM | H52: m2 | I52: 8338.55 | J52: 80.07 | K52: =I52*J52 -> 667667.7
B53: 52 | C53: 4.8 | D53: 24.06.02 | E53: ACESSOS - LADO SANTOS E GUARUJÁ | F53: OBRAS DE ARTE CORRENTE E DRENAGEM | G53: BARRA DE AÇO CA-50 | H53: kg | I53: 270419.44 | J53: 8.52 | K53: =I53*J53 -> 2303973.6
B54: 53 | C54: 4.9 | D54: 24.07.01 | E54: ACESSOS - LADO SANTOS E GUARUJÁ | F54: OBRAS DE ARTE CORRENTE E DRENAGEM | G54: CONCRETO fck 10 MPa | H54: m3 | I54: 453.61 | J54: 386.3 | K54: =I54*J54 -> 175229.54
B55: 54 | C55: 4.10 | D55: 24.07.02 | E55: ACESSOS - LADO SANTOS E GUARUJÁ | F55: OBRAS DE ARTE CORRENTE E DRENAGEM | G55: CONCRETO fck 15 MPa | H55: m3 | I55: 1241.07 | J55: 426.19 | K55: =I55*J55 -> 528931.62
B56: 55 | C56: 4.11 | D56: 24.07.04 | E56: ACESSOS - LADO SANTOS E GUARUJÁ | F56: OBRAS DE ARTE CORRENTE E DRENAGEM | G56: CONCRETO fck 20 MPa | H56: m3 | I56: 1248.84 | J56: 455.28 | K56: =I56*J56 -> 568571.88
B57: 56 | C57: 4.12 | D57: 24.07.05 | E57: ACESSOS - LADO SANTOS E GUARUJÁ | F57: OBRAS DE ARTE CORRENTE E DRENAGEM | G57: CONCRETO fck 25 MPa | H57: m3 | I57: 1049.76 | J57: 467.63 | K57: =I57*J57 -> 490899.27
... B79: 78 | C79: 4.34 | D79: 24.88.17.02.15 | E79: ACESSOS - LADO SANTOS E GUARUJÁ | F79: OBRAS DE ARTE CORRENTE E DRENAGEM | G79: LAJOTA PRÉ MOLDADA DE CONCRETO E=7CM JUNTA DE GRAMA | H79: m2 | I79: 10386 | J79: 55.24 | K79: =I79*J79 -> 573722.64
B80: 79 | C80: 5 | D80: 25 | E80: ACESSOS - LADO SANTOS E GUARUJÁ | F80: OBRAS DE CONTENÇÃO GEOTÉCNICA
B81: 80 | C81: 5.1 | D81: 25.21.88.05.01 | E81: ACESSOS - LADO SANTOS E GUARUJÁ | F81: OBRAS DE CONTENÇÃO GEOTÉCNICA | G81: DEMOLIÇÃO DE GUIA EM CONCRETO ARMADO -PAREDE DIAFRAGMA | H81: m3 | I81: 1562.9 | J81: 294.37 | K81: =I81*J81 -> 460070.87
B82: 81 | C82: 5.2 | D82: 22.02.01 | E82: ACESSOS - LADO SANTOS E GUARUJÁ | F82: OBRAS DE CONTENÇÃO GEOTÉCNICA | G82: ESCAVAÇÃO E CARGA DE MATERIAL DE 1ª/2ª CATEGORIA | H82: m3 | I82: 199090 | J82: 4.9 | K82: =I82*J82 -> 975541
B83: 82 | C83: 5.3 | D83: 22.02.05 | E83: ACESSOS - LADO SANTOS E GUARUJÁ | F83: OBRAS DE CONTENÇÃO GEOTÉCNICA | G83: ESCAVAÇÃO E CARGA DE SOLO MOLE SOB LÂMINA D' ÁGUA | H83: m3 | I83: 90000 | J83: 10.66 | K83: =I83*J83 -> 959400
B84: 83 | C84: 5.4 | D84: 22.02.09 | E84: ACESSOS - LADO SANTOS E GUARUJÁ | F84: OBRAS DE CONTENÇÃO GEOTÉCNICA | G84: ESPALHAMENTO / REGULARIZAÇÃO / COMPACTAÇÃO DE MATERIAL EM BOTA-FORA. | H84: m3 | I84: 268240 | J84: 2.21 | K84: =I84*J84 -> 592810.4
B85: 84 | C85: 5.5 | D85: 22.03.05 | E85: ACESSOS - LADO SANTOS E GUARUJÁ | F85: OBRAS DE CONTENÇÃO GEOTÉCNICA | G85: TRANSPORTE DE MATERIAL DE 1ª/2ª CATEGORIA ATÉ 15 km | H85: m3 x km | I85: 2836200 | J85: 1.26 | K85: =I85*J85 -> 3573612
B86: 85 | C86: 5.6 | D86: 22.03.06 | E86: ACESSOS - LADO SANTOS E GUARUJÁ | F86: OBRAS DE CONTENÇÃO GEOTÉCNICA | G86: TRANSPORTE DE MATERIAL DE 1ª/2ª CATEGORIA ALÉM DE 15 km | H86: m3 x km | I86: 7129600 | J86: 0.99 | K86: =I86*J86 -> 7058304
B87: 86 | C87: 5.7 | D87: 22.03.10 | E87: ACESSOS - LADO SANTOS E GUARUJÁ | F87: OBRAS DE CONTENÇÃO GEOTÉCNICA | G87: TRANSPORTE DE SOLO MOLE ALÉM DE 2 km | H87: m3 x km | I87: 4394542.1 | J87: 2.41 | K87: =I87*J87 -> 10590846
B88: 87 | C88: 5.8 | D88: 22.04.01 | E88: ACESSOS - LADO SANTOS E GUARUJÁ | F88: OBRAS DE CONTENÇÃO GEOTÉCNICA | G88: COMPACTAÇÃO DE ATERRO MAIOR/IGUAL 95% PN | H88: m3 | I88: 189080 | J88: 3.01 | K88: =I88*J88 -> 569130.8
B89: 88 | C89: 5.9 | D89: 22.06.04 | E89: ACESSOS - LADO SANTOS E GUARUJÁ | F89: OBRAS DE CONTENÇÃO GEOTÉCNICA | G89: FUNDAÇÃO DE ATERRO COM PEDRA RACHÃO | H89: m3 | I89: 24396 | J89: 101.3 | K89: =I89*J89 -> 2471314.8
B90: 89 | C90: 5.10 | D90: 24.01.01 | E90: ACESSOS - LADO SANTOS E GUARUJÁ | F90: OBRAS DE CONTENÇÃO GEOTÉCNICA | G90: VOLUME DE ATERRO COMPACTADO | H90: m3 | I90: 25662.52 | J90: 8.52 | K90: =I90*J90 -> 218644.67
B91: 90 | C91: 5.11 | D91: 24.12.02 | E91: ACESSOS - LADO SANTOS E GUARUJÁ | F91: OBRAS DE CONTENÇÃO GEOTÉCNICA | G91: ENCHIMENTO DE VALA COM AREIA LAVADA | H91: m3 | I91: 1100 | J91: 131.19 | K91: =I91*J91 -> 144309
B92: 91 | C92: 5.12 | D92: 24.14.01.09 | E92: ACESSOS - LADO SANTOS E GUARUJÁ | F92: OBRAS DE CONTENÇÃO GEOTÉCNICA | G92: MANTA GEOTEXTIL NÃO TECIDA RESISTENCIA LONGITUDIANAL 31 kN/m | H92: m2 | I92: 40660 | J92: 16.95 | K92: =I92*J92 -> 689187
... B115: 114 | C115: 5.35 | D115: 29.88.07.08 | E115: ACESSOS - LADO SANTOS E GUARUJÁ | F115: OBRAS DE CONTENÇÃO GEOTÉCNICA | G115: FORNECIMENTO DE PERFIL METÁLICO CS-350 MASSA LINEAR DE 144 kg/m -EXECUÇÃO DE ESTRONCAS | H115: kg | I115: 203812.21 | J115: 10.76 | K115: =I115*J115 -> 2193019.4
B116: 115 | C116: 6 | D116: 26 | E116: ACESSOS - LADO SANTOS E GUARUJÁ | F116: OBRAS DE ARTE ESPECIAIS
B117: 116 | C117: 6.1 | D117: 22.02.05 | E117: ACESSOS - LADO SANTOS E GUARUJÁ | F117: OBRAS DE ARTE ESPECIAIS | G117: ESCAVAÇÃO E CARGA DE SOLO MOLE SOB LÂMINA D' ÁGUA | H117: m3 | I117: 9836 | J117: 10.66 | K117: =I117*J117 -> 104851.76
B118: 117 | C118: 6.2 | D118: 24.12.08 | E118: ACESSOS - LADO SANTOS E GUARUJÁ | F118: OBRAS DE ARTE ESPECIAIS | G118: COMPACTAÇÃO MANUAL COM REATERRO SOLO LOCAL | H118: m3 | I118: 2067 | J118: 24.16 | K118: =I118*J118 -> 49938.72
B119: 118 | C119: 6.3 | D119: 25.20.01 | E119: ACESSOS - LADO SANTOS E GUARUJÁ | F119: OBRAS DE ARTE ESPECIAIS | G119: SOLO REFORÇADO TIPO GREIDE COM ALTURA DE 0 A 6 METROS | H119: m2 | I119: 19520 | J119: 716.86 | K119: =I119*J119 -> 13993107
B120: 119 | C120: 6.4 | D120: 25.88.04.06.02 | E120: ACESSOS - LADO SANTOS E GUARUJÁ | F120: OBRAS DE ARTE ESPECIAIS | G120: FORNECIMENTO E CRAVAÇÃO DE COMBINED WALL WITH TUBULAR PILES COM COMPRIMENTO ATÉ 50,0 METROS, EM AÇO CARBONO COM RESISTÊNCIA CARACTERISTICA SUPERIOR A 350 Mpa, INCLUSIVE JUNTA SELANTE POLIMÉRICA ENTRE ELEMENTOS | H120: kg | I120: 311987.7 | J120: 10.89 | K120: =I120*J120 -> 3397546.1
B121: 120 | C121: 6.5 | D121: 26.01.01 | E121: ACESSOS - LADO SANTOS E GUARUJÁ | F121: OBRAS DE ARTE ESPECIAIS | G121: ESCAVAÇÃO MANUAL PARA OBRAS SEM EXPLOSIVO | H121: m3 | I121: 5795 | J121: 50.17 | K121: =I121*J121 -> 290735.15
B122: 121 | C122: 6.6 | D122: 26.02.05 | E122: ACESSOS - LADO SANTOS E GUARUJÁ | F122: OBRAS DE ARTE ESPECIAIS | G122: ESTACA CONCRETO PRÉ-MOLDADO -70/80 T | H122: m | I122: 1120 | J122: 185.58 | K122: =I122*J122 -> 207849.6
B123: 122 | C123: 6.7 | D123: 26.02.14 | E123: ACESSOS - LADO SANTOS E GUARUJÁ | F123: OBRAS DE ARTE ESPECIAIS | G123: ESTACÃO EM SOLO D = 1,20M | H123: m | I123: 320 | J123: 1808.32 | K123: =I123*J123 -> 578662.4
B124: 123 | C124: 6.8 | D124: 26.02.15 | E124: ACESSOS - LADO SANTOS E GUARUJÁ | F124: OBRAS DE ARTE ESPECIAIS | G124: ESTACÃO EM SOLO D = 1,40M | H124: m | I124: 1216 | J124: 2361.98 | K124: =I124*J124 -> 2872167.7
B125: 124 | C125: 6.9 | D125: 26.02.18 | E125: ACESSOS - LADO SANTOS E GUARUJÁ | F125: OBRAS DE ARTE ESPECIAIS | G125: ESTACÃO EM SOLO D = 1,80M | H125: m | I125: 1728 | J125: 3766.11 | K125: =I125*J125 -> 6507838.1
B126: 125 | C126: 6.10 | D126: 26.04.04 | E126: ACESSOS - LADO SANTOS E GUARUJÁ | F126: OBRAS DE ARTE ESPECIAIS | G126: CIMBRAMENTO METALICO PARA PONTES E VIADUTOS | H126: m3 | I126: 68659 | J126: 56.65 | K126: =I126*J126 -> 3889532.4
B127: 126 | C127: 6.11 | D127: 26.04.06 | E127: ACESSOS - LADO SANTOS E GUARUJÁ | F127: OBRAS DE ARTE ESPECIAIS | G127: ANDAIME TUBULAR | H127: m3 | I127: 950 | J127: 18.12 | K127: =I127*J127 -> 17214
B128: 127 | C128: 6.12 | D128: 26.05.01 | E128: ACESSOS - LADO SANTOS E GUARUJÁ | F128: OBRAS DE ARTE ESPECIAIS | G128: FORMA PLANA PARA CONCRETO COMUM | H128: m2 | I128: 23169.08 | J128: 80.07 | K128: =I128*J128 -> 1855148.2
... B155: 154 | C155: 6.39 | D155: 29.88.23.02 | E155: ACESSOS - LADO SANTOS E GUARUJÁ | F155: OBRAS DE ARTE ESPECIAIS | G155: MERGULHADORES DE INSPEÇÃO -EQUIPE COMPOSTA POR 4 MERGULHADORES, 2 SUBMERSOS E 2 EM TERRA | H155: h | I155: 1320 | J155: 675 | K155: =I155*J155 -> 891000
B156: 155 | C156: 7 | D156: 28 | E156: ACESSOS - LADO SANTOS E GUARUJÁ | F156: SINALIZAÇÃO E ELEMENTOS DE SEGURANÇA
B157: 156 | C157: 7.1 | D157: 28.88.70.05 | E157: ACESSOS - LADO SANTOS E GUARUJÁ | F157: SINALIZAÇÃO E ELEMENTOS DE SEGURANÇA | G157: POSTE COMPOSTO PARA SINALIZAÇÃO | H157: unid | I157: 6 | J157: 3807 | K157: =I157*J157 -> 22842
B158: 157 | C158: 7.2 | D158: 28.88.70.01 | E158: ACESSOS - LADO SANTOS E GUARUJÁ | F158: SINALIZAÇÃO E ELEMENTOS DE SEGURANÇA | G158: BPC -BRAÇO PROJETADO EM COLUNA (SINALIZAÇÃO VERTICAL) -PP DA CET-SP - A2-191-DSV3 -COLUNA E BRAÇO 5x5,25 | H158: unid | I158: 9 | J158: 3132 | K158: =I158*J158 -> 28188
B159: 158 | C159: 7.3 | D159: 28.88.70.03 | E159: ACESSOS - LADO SANTOS E GUARUJÁ | F159: SINALIZAÇÃO E ELEMENTOS DE SEGURANÇA | G159: BRAÇO PROJETADO (SINALIZAÇÃO SEMAFÓRICA) -PP'S DA CET - CET-21, CET-22, CET-28, CET-28 e CET-36 . | H159: unid | I159: 10 | J159: 2862 | K159: =I159*J159 -> 28620
B160: 159 | C160: 7.4 | D160: 28.88.70.04 | E160: ACESSOS - LADO SANTOS E GUARUJÁ | F160: SINALIZAÇÃO E ELEMENTOS DE SEGURANÇA | G160: POSTE SIMPLES PARA SINALIZAÇÃO, DE ACORDO COM A CET-22 | H160: unid | I160: 16 | J160: 3483 | K160: =I160*J160 -> 55728
B161: 160 | C161: 7.5 | D161: 28.88.70.02 | E161: ACESSOS - LADO SANTOS E GUARUJÁ | F161: SINALIZAÇÃO E ELEMENTOS DE SEGURANÇA | G161: FOCO SEMAFÓRICO PP'S GCR-1057-CONJUNTO 200 CONV. BP E GCR-1056-CONJUNTO 200 CONV. CS | H161: unid | I161: 34 | J161: 3267 | K161: =I161*J161 -> 111078
B162: 161 | C162: 7.6 | D162: 28.06.30 | E162: ACESSOS - LADO SANTOS E GUARUJÁ | F162: SINALIZAÇÃO E ELEMENTOS DE SEGURANÇA | G162: SUPORTE DE PLACAS DE SOLO ECOLÓGICO E COLAPSIVEL 75X75 mm | H162: m | I162: 64 | J162: 80.24 | K162: =I162*J162 -> 5135.36
B163: 162 | C163: 7.7 | D163: 28.02.04.01 | E163: ACESSOS - LADO SANTOS E GUARUJÁ | F163: SINALIZAÇÃO E ELEMENTOS DE SEGURANÇA | G163: FORNECIMENTO, TRANSPORTE E FIXAÇÃO DE SEMI-PÓRTICO TUBULAR EM BALANCO VÃO DE 5,10 m | H163: unid | I163: 76 | J163: 17001.17 | K163: =I163*J163 -> 1292088.9
B164: 163 | C164: 7.8 | D164: 28.02.01.01 | E164: ACESSOS - LADO SANTOS E GUARUJÁ | F164: SINALIZAÇÃO E ELEMENTOS DE SEGURANÇA | G164: FORNECIMENTO,TRANSPORTE E FIXAÇÃO DE PÓRTICO TUBULAR METÁLICO VÃO DE 15,20 m | H164: unid | I164: 80 | J164: 38060.16 | K164: =I164*J164 -> 3044812.8
B165: 164 | C165: 7.9 | D165: 28.01.05.01 | E165: ACESSOS - LADO SANTOS E GUARUJÁ | F165: SINALIZAÇÃO E ELEMENTOS DE SEGURANÇA | G165: FORNECIMENTO E TRANSPORTE DE PLACA DE AÇO GT+AI | H165: m2 | I165: 86 | J165: 897.06 | K165: =I165*J165 -> 77147.16
B166: 165 | C166: 7.10 | D166: 28.01.04.01 | E166: ACESSOS - LADO SANTOS E GUARUJÁ | F166: SINALIZAÇÃO E ELEMENTOS DE SEGURANÇA | G166: FORNECIMENTO E TRANSPORTE DE PLACA DE AÇO GT+GT | H166: m2 | I166: 168.27 | J166: 710.78 | K166: =I166*J166 -> 119602.95
B167: 166 | C167: 7.11 | D167: 28.01.24.01 | E167: ACESSOS - LADO SANTOS E GUARUJÁ | F167: SINALIZAÇÃO E ELEMENTOS DE SEGURANÇA | G167: COLOCAÇAO DE PLACA EM SUPÕRTE DE MADEIRA/METÁLICO -SOLO | H167: m2 | I167: 270.4 | J167: 44.06 | K167: =I167*J167 -> 11913.824
B168: 167 | C168: 7.12 | D168: 28.06.12 | E168: ACESSOS - LADO SANTOS E GUARUJÁ | F168: SINALIZAÇÃO E ELEMENTOS DE SEGURANÇA | G168: SUPORTE TUBULAR GALVANIZADO 2 1/2 | H168: m | I168: 271.5 | J168: 81.51 | K168: =I168*J168 -> 22129.965
... B174: 173 | C174: 7.18 | D174: 28.03.13 | E174: ACESSOS - LADO SANTOS E GUARUJÁ | F174: SINALIZAÇÃO E ELEMENTOS DE SEGURANÇA | G174: TACHA MONODIRECIONAL COM REFLETIVO PLÁSTICO | H174: unid | I174: 4655 | J174: 14.23 | K174: =I174*J174 -> 66240.65
B175: 174 | C175: 8 | D175: 30 | E175: ACESSOS - LADO SANTOS E GUARUJÁ | F175: SERVIÇOS DE PROTEÇÃO AO MEIO AMBIENTE E PAISAGISMO
...

Sheet INSUMOS
A1: Planilha: 00011 - TUNEL SUBMERSO SIGMA P82
A3: Codigo | B3: Descricao | C3: Unid | D3: Qtde | E3: Qtde Improd | F3: Custo Unit | G3: Valor | H3: % | I3: % Acum. | J3: % s/ Tot | K3: % Acum
A4: IM1920 | B4: FORNECIMENTO DE AÇO CA-50, CORTADO E DOBRADO | C4: KG | D4: 57547713 | F4: 2.53 | G4: 1.4559571e+08 | H4: 18.45 | I4: 18.45 | J4: 10.18 | K4: 10.18
A5: IM1273 | B5: TUBO DE AÇO CARBONO Ø2M E CONECTORES - COMBWALL | C5: KG | D5: 18916320 | F5: 4.5 | G5: 85123438 | H5: 10.79 | I5: 29.24 | J5: 5.95 | K5: 16.13
A6: IM1102 | B6: CIMENTO PORTLAND CP III RS 40 | C6: T | D6: 251407.65 | F6: 314.55 | G6: 79080297 | H6: 10.02 | I6: 39.26 | J6: 5.53 | K6: 21.66
A7: IM0704 | B7: AREIA LAVADA | C7: M3 | D7: 529015.05 | F7: 85 | G7: 44966289 | H7: 5.7 | I7: 44.96 | J7: 3.14 | K7: 24.8
A8: IM1281 | B8: INJEÇÃO DE COLUNA JET GROUTING EM SOLO NATURAL, INDEPENDENTE DIAMETRO | C8: M3 | D8: 125288.41 | F8: 250 | G8: 31322102 | H8: 3.97 | I8: 48.93 | J8: 2.19 | K8: 26.99
A9: IM0201 | B9: CIMENTO PORTLAND CP II-32(A GRANEL) | C9: KG | D9: 75262873 | F9: 0.3 | G9: 22578862 | H9: 2.86 | I9: 51.79 | J9: 1.58 | K9: 28.57
A10: IM1916 | B10: INSTALAÇÃO DE CANTEIRO DE OBRAS | C10: GB | D10: 1 | F10: 21625344 | G10: 21625344 | H10: 2.74 | I10: 54.53 | J10: 1.51 | K10: 30.08
A11: IN0035 | B11: BRITA 1 | C11: M3 | D11: 268819.26 | F11: 75 | G11: 20161441 | H11: 2.55 | I11: 57.08 | J11: 1.41 | K11: 31.49
A12: IM1106 | B12: RACHÃO | C12: M3 | D12: 254314.48 | F12: 74 | G12: 18819271 | H12: 2.38 | I12: 59.46 | J12: 1.32 | K12: 32.81
A13: IM1931 | B13: MATERIAL CONSUMO DE CONSUMO COMBWALL | C13: KG | D13: 18008685 | F13: 0.91 | G13: 16387904 | H13: 2.08 | I13: 61.54 | J13: 1.15 | K13: 33.96
A14: IM1881 | B14: DRAGAGEM / REMOÇÃO DE MATERIAL MARINHO (PROFUNDIDADES DE 15,0 A 32,0 m), INCLUSIVE TRANSPORTE E DEPOSIÇÃO EM LOCAL APROPRIADO (POLIGONO DE DEPOSIÇÃO OCEANICA) | C14: M3 | D14: 138086.55 | F14: 117.26 | G14: 16192029 | H14: 2.05 | I14: 63.59 | J14: 1.13 | K14: 35.09
A15: IM0002 | B15: OLEO DIESEL | C15: L | D15: 7030663.7 | F15: 2.26 | G15: 15890003 | H15: 2.01 | I15: 65.6 | J15: 1.11 | K15: 36.2
... A806: IH1028 | B806: OPERATI MEZZI MARITIMI | C806: H | D806: 10.805211 | F806: 31.26 | G806: 0 | H806: 0 | I806: 100 | J806: 0 | K806: 13.67
A807: IE5084 | B807: MARINE EQUIPEMENT FOR DRAGAGEM - 15 | C807: H | D807: 7799.9894 | E807: 21.802 | F807: 25317.59 | G807: 1.9797871e+08 | H807: 43.66 | I807: 43.66 | J807: 13.84 | K807: 13.84
A808: IE0404 | B808: CAMINHÃO BASCULANTE 25 T | C808: H | D808: 325120.33 | E808: 790.662 | F808: 123.69 | G808: 40156777 | H808: 8.85 | I808: 52.51 | J808: 2.81 | K808: 16.65
A809: IE0427 | B809: CAMINHÃO BETONEIRA 8M³ | C809: H | D809: 84197.327 | E809: 370989.83 | F809: 144.41 | G809: 18022531 | H809: 3.97 | I809: 56.48 | J809: 1.26 | K809: 17.91
A810: IE5056 | B810: EQUIPAMENTO PARA INJEÇÃO DE JET GROUTING | C810: H | D810: 32640.431 | E810: 732.796 | F810: 534.83 | G810: 17611295 | H810: 3.88 | I810: 60.36 | J810: 1.23 | K810: 19.14
A811: IE5043 | B811: GRUPO DE ESCAVAÇÃO COM KELLY | C811: H | D811: 37613.307 | E811: 3313.294 | F811: 451.32 | G811: 16975641 | H811: 3.74 | I811: 64.1 | J811: 1.19 | K811: 20.33
A812: IE5087 | B812: MARINE EQUIPEMENT FOR LANCIAMENTO RACHAO | C812: H | D812: 3119.9993 | E812: 63.571 | F812: 4357 | G812: 13848748 | H812: 3.05 | I812: 67.15 | J812: 0.97 | K812: 21.3
A813: IE5089 | B813: MARINE EQUIPEMENT FOR DRAGAGEM E LANÇAMENTO DE AREIA | C813: H | D813: 2423.5741 | E813: 40.406 | F813: 5216.51 | G813: 12837439 | H813: 2.83 | I813: 69.98 | J813: 0.9 | K813: 22.2
A814: IE5080 | B814: CENTRAL DOSADORA DE CONCRETO | C814: H | D814: 15054.749 | F814: 803 | G814: 12088605 | H814: 2.67 | I814: 72.65 | J814: 0.84 | K814: 23.04
A815: IE5078 | B815: GRUPO DE EQUIPAMENTO HIDROFRESA | C815: H | D815: 9638.5207 | E815: 732.796 | F815: 1199.88 | G815: 11565103 | H815: 2.55 | I815: 75.2 | J815: 0.81 | K815: 23.85
A816: IE0201 | B816: COMPRESSOR DE AR - 295 PCM | C816: H | D816: 23000.485 | E816: 469887.15 | F816: 71.01 | G816: 8892589.9 | H816: 1.96 | I816: 77.16 | J816: 0.62 | K816: 24.47
A817: IE5075 | B817: CAMINHÃO DUMPER 25T | C817: H | D817: 102210.84 | E817: 31412.088 | F817: 70 | G817: 7153321.8 | H817: 1.58 | I817: 78.74 | J817: 0.5 | K817: 24.97
A818: IE5040 | B818: PÁ CARREGADEIRA W170ZB - 183 HP | C818: H | D818: 46177.857 | E818: 34117.54 | F818: 103.5 | G818: 6072382.6 | H818: 1.34 | I818: 80.08 | J818: 0.42 | K818: 25.39
A819: IE5083 | B819: MARINE EQUIPEMENT FOR COMBIWALL | C819: H | D819: 1596.508 | E819: 72.114 | F819: 3519.23 | G819: 5777115.5 | H819: 1.27 | I819: 81.35 | J819: 0.4 | K819: 25.79
A820: IE0406 | B820: CAMINHÃO PIPA 18.000 LT | C820: H | D820: 12271.396 | E820: 93265.525 | F820: 126.23 | G820: 5171144 | H820: 1.14 | I820: 82.49 | J820: 0.36 | K820: 26.15
A821: IE5064 | B821: GUINDASTE SOBRE PNEUS 30T | C821: H | D821: 34301.528 | E821: 474874.38 | F821: 150 | G821: 4972469.8 | H821: 1.1 | I821: 83.59 | J821: 0.35 | K821: 26.5
A822: IE5070 | B822: GUINDASTE SOBRE ESTEIRAS 100T | C822: H | D822: 10211.418 | E822: 1152.836 | F822: 460 | G822: 4697046.1 | H822: 1.04 | I822: 84.63 | J822: 0.33 | K822: 26.83
A823: IE5054 | B823: SONDA PERFURATRIZ | C823: H | D823: 24313.52 | E823: 138.08 | F823: 178.22 | G823: 4349222.6 | H823: 0.96 | I823: 85.59 | J823: 0.3 | K823: 27.13
A824: IE0147 | B824: USINA DE ASFALTO A QUENTE : CIFALI : CIFALI MAGNUM 120 - | C824: H | D824: 466.3802 | F824: 8223.76 | G824: 3835437.1 | H824: 0.85 | I824: 86.44 | J824: 0.27 | K824: 27.4
A825: IE5072 | B825: GUINDASTE SOBRE ESTEIRAS 250T | C825: H | D825: 6227.0418 | E825: 360.893 | F825: 600 | G825: 3783551.9 | H825: 0.83 | I825: 87.27 | J825: 0.26 | K825: 27.66
A826: IE5077 | B826: TORRE DE ILUMINAÇÃO | C826: H | D826: 184648.4 | E826: 386155.86 | F826: 20 | G826: 3605805 | H826: 0.8 | I826: 88.07 | J826: 0.25 | K826: 27.91
A827: IE5052 | B827: COMPRESSOR DE AR 21,9 M3/1' | C827: H | D827: 32390.86 | E827: 40116.798 | F827: 84.2 | G827: 3356917.2 | H827: 0.74 | I827: 88.81 | J827: 0.23 | K827: 28.14
A828: IE5026 | B828: CAMINHÃO MUNCK 5T | C828: H | D828: 10568.502 | E828: 71212.651 | F828: 101.24 | G828: 3262404.9 | H828: 0.72 | I828: 89.53 | J828: 0.23 | K828: 28.37
A829: IE5082 | B829: DRIVER MARINE EQUIPEMENT FOR DRAGAGEM | C829: H | D829: 42119.99 | E829: 209.884 | F829: 77 | G829: 3240738.2 | H829: 0.71 | I829: 90.24 | J829: 0.23 | K829: 28.6
A830: IE5045 | B830: DESARENADOR COMPLETO 200 M3/HR | C830: H | D830: 31102.471 | E830: 1441.297 | F830: 85.74 | G830: 2719913.3 | H830: 0.6 | I830: 90.84 | J830: 0.19 | K830: 28.79
A831: IE5091 | B831: MARTELLO VIBRO PER TUBI DI ACCIAIO + POWER PACK | C831: H | D831: 4620.8486 | E831: 1962.946 | F831: 500 | G831: 2341129.1 | H831: 0.52 | I831: 91.36 | J831: 0.16 | K831: 28.95
A832: IE5046 | B832: MOTOBOMBA DIESEL DE AGUA SUBMERSIVEL 15 MC/HR | C832: H | D832: 100758.8 | E832: 5812.606 | F832: 22.37 | G832: 2286149.8 | H832: 0.5 | I832: 91.86 | J832: 0.16 | K832: 29.11
A833: IE5049 | B833: MOTOSOLDADOR | C833: H | D833: 15693.058 | E833: 461736.25 | F833: 17.19 | G833: 2235938.4 | H833: 0.49 | I833: 92.35 | J833: 0.16 | K833: 29.27
A834: IE5031 | B834: ESCAVADEIRA HIDRAULICA 30T | C834: H | D834: 14570.016 | E834: 319.989 | F834: 140 | G834: 2038196.2 | H834: 0.45 | I834: 92.8 | J834: 0.14 | K834: 29.41
A835: IE0016 | B835: CARREGADEIRA DE PNEUS - 1,91 M3, COMBUSTIVEL E OPERAÇÃO | C835: H | D835: 12832.382 | E835: 15714.964 | F835: 130.71 | G835: 2001377 | H835: 0.44 | I835: 93.24 | J835: 0.14 | K835: 29.55
A836: IE5066 | B836: GUINDASTE SOBRE PNEUS 60T | C836: H | D836: 10200.897 | E836: 42238.458 | F836: 193 | G836: 1952121.2 | H836: 0.43 | I836: 93.67 | J836: 0.14 | K836: 29.69
A837: IE5055 | B837: MOTOBOMBA 700HP | C837: H | D837: 23001.91 | F837: 83.42 | G837: 1917899.5 | H837: 0.42 | I837: 94.09 | J837: 0.13 | K837: 29.82
A838: IE5039 | B838: CAMINHÃO ABASTECEDOR 10.000LT | C838: H | D838: 16216.951 | E838: 0.405 | F838: 115.51 | G838: 1876778.1 | H838: 0.41 | I838: 94.5 | J838: 0.13 | K838: 29.95
A839: IE5050 | B839: EXTRATOR ESTACAS PRANCHAS | C839: H | D839: 11528.317 | E839: 48996.187 | F839: 65.87 | G839: 1844606 | H839: 0.41 | I839: 94.91 | J839: 0.13 | K839: 30.08
A840: IE5053 | B840: CAMINHÃO TOCO 5,3 M3 | C840: H | D840: 13782.185 | E840: 38459.761 | F840: 68.34 | G840: 1758493.4 | H840: 0.39 | I840: 95.3 | J840: 0.12 | K840: 30.2
A841: IE5092 | B841: MARTELLO VIBRO PER PALANCOLE + POWER PACK | C841: H | D841: 3300.6318 | E841: 324.156 | F841: 500 | G841: 1620781.7 | H841: 0.36 | I841: 95.66 | J841: 0.11 | K841: 30.31
A842: IE5057 | B842: GRUPO GERADOR 136 KVA | C842: H | D842: 25753.685 | F842: 61.45 | G842: 1580983.1 | H842: 0.35 | I842: 96.01 | J842: 0.11 | K842: 30.42
A843: IE0306 | B843: VIBRADOR ELETRICO | C843: H | D843: 61582.211 | E843: 645912.91 | F843: 6.43 | G843: 1293359.3 | H843: 0.29 | I843: 96.3 | J843: 0.09 | K843: 30.51
A844: IE5061 | B844: CORREIA TRANSPORTADORA | C844: UN | D844: 4.073431 | F844: 300000 | G844: 1222734.2 | H844: 0.27 | I844: 96.57 | J844: 0.09 | K844: 30.6
A845: IE5079 | B845: CAMINHÃO COM BOMBA DE CONCRETO | C845: H | D845: 8903.4739 | E845: 6746.879 | F845: 94 | G845: 1071371.9 | H845: 0.24 | I845: 96.81 | J845: 0.07 | K845: 30.67
A846: IE5058 | B846: GRUPPO DI SCAVO PALI TRIVELLATI | C846: H | D846: 2281.2299 | F846: 464.71 | G846: 1060100.7 | H846: 0.23 | I846: 97.04 | J846: 0.07 | K846: 30.74
A847: IE5068 | B847: GUINDASTE SOBRE ESTEIRAS 50T | C847: H | D847: 4654.1973 | E847: 10886.764 | F847: 193 | G847: 1013287 | H847: 0.22 | I847: 97.26 | J847: 0.07 | K847: 30.81
A848: IE5086 | B848: DRIVER MARINE EQUIPEMENT FOR LANCIAMENTO RACHAO | C848: H | D848: 12480 | F848: 77 | G848: 961437.8 | H848: 0.21 | I848: 97.47 | J848: 0.07 | K848: 30.88
A849: IE0202 | B849: COMPRESSOR DE AR 11 M3/1' | C849: H | D849: 14580.286 | E849: 1311.61 | F849: 59.4 | G849: 887202.68 | H849: 0.2 | I849: 97.67 | J849: 0.06 | K849: 30.94
A850: IE5038 | B850: ROLO VIBRATORIO PÉ DE CARNEIRO VAP70PTCR 11,7T | C850: H | D850: 7864.4901 | F850: 108.37 | G850: 845485.22 | H850: 0.19 | I850: 97.86 | J850: 0.06 | K850: 31
A851: IE5093 | B851: GRUPPO DI SCAVO PALI TRIVELLATI | C851: H | D851: 1614.9479 | E851: 379.986 | F851: 500 | G851: 807553.88 | H851: 0.18 | I851: 98.04 | J851: 0.06 | K851: 31.06
A852: IE5090 | B852: DRIVER MARINE EQUIPEMENT FOR LANCIAMENTO LANÇAMENTO DE AREIA | C852: H | D852: 9444.7018 | F852: 77 | G852: 727927.84 | H852: 0.16 | I852: 98.2 | J852: 0.05 | K852: 31.11
A853: IE5060 | B853: CONJUNTO DE BRITAGEM MOVEL 100T/H | C853: UN | D853: 0.71285 | F853: 1000000 | G853: 713555.29 | H853: 0.16 | I853: 98.36 | J853: 0.05 | K853: 31.16
A854: IE5005 | B854: BOMBA ESTACIONARIA DE CONCRETO - AQUISIÇÃO | C854: UN | D854: 2.8 | F854: 252000 | G854: 706029 | H854: 0.16 | I854: 98.52 | J854: 0.05 | K854: 31.21
A855: IE5088 | B855: SOMMOZZATORE | C855: H | D855: 4266.6666 | F855: 135 | G855: 576188.78 | H855: 0.13 | I855: 98.65 | J855: 0.04 | K855: 31.25
A856: IE0509 | B856: GRUPO GERADOR 30 KVA | C856: H | D856: 27266.213 | E856: 7213.66 | F856: 17.91 | G856: 512604.31 | H856: 0.11 | I856: 98.76 | J856: 0.04 | K856: 31.29
A857: IE5076 | B857: CAMINHÃO CAÇAMBA 40T | C857: H | D857: 4465.6793 | E857: 202855.26 | F857: 80 | G857: 458773.49 | H857: 0.1 | I857: 98.86 | J857: 0.03 | K857: 31.32
A858: IE0924 | B858: EQUIP. PARA SOLDA : MAX BANTAM : BANTAM 250 SERRALHEIRO - | C858: H | D858: 113083.22 | E858: 1015902.8 | F858: 3.39 | G858: 382746.99 | H858: 0.08 | I858: 98.94 | J858: 0.03 | K858: 31.35
A859: IE5036 | B859: MOTONIVELADORA RG 140B | C859: H | D859: 4260.7554 | F859: 81.07 | G859: 352713.34 | H859: 0.08 | I859: 99.02 | J859: 0.02 | K859: 31.37
A860: IE5047 | B860: PA CARREGADEIRA CAT 928G | C860: H | D860: 4770.7225 | E860: 1027.88 | F860: 73.42 | G860: 349699.41 | H860: 0.08 | I860: 99.1 | J860: 0.02 | K860: 31.39
A861: IE5015 | B861: MOBILIZAÇÃO DE EQUIPAMENTO DE JET GROUTING | C861: VB | D861: 3 | F861: 110000 | G861: 329508.52 | H861: 0.07 | I861: 99.17 | J861: 0.02 | K861: 31.41
A862: IE5041 | B862: ROLO VIBRATORIO LISO VAP70LTCR 14,9T | C862: H | D862: 2916.8017 | F862: 107.95 | G862: 315021.14 | H862: 0.07 | I862: 99.24 | J862: 0.02 | K862: 31.43
A863: IE5008 | B863: CAMINHÃO BETONEIRA 8M³ - AQUISIÇÃO | C863: UN | D863: 0.746882 | F863: 375000 | G863: 280005.58 | H863: 0.06 | I863: 99.3 | J863: 0.02 | K863: 31.45
A864: IE5016 | B864: SILO DE CIMENTO METALICO 100T | C864: UN | D864: 2.1 | F864: 130000 | G864: 273128.74 | H864: 0.06 | I864: 99.36 | J864: 0.02 | K864: 31.47
A865: IE5037 | B865: TRATOR AGRÍCOLA | C865: H | D865: 5418.3206 | F865: 50 | G865: 263580.33 | H865: 0.06 | I865: 99.42 | J865: 0.02 | K865: 31.49
A866: IE0210 | B866: MARTELETE - ROMPEDOR 33 KG | C866: H | D866: 12866.693 | E866: 1045.378 | F866: 16.66 | G866: 229747.26 | H866: 0.05 | I866: 99.47 | J866: 0.02 | K866: 31.51
A867: IE5059 | B867: GRÙ DI SERVIZIO DA 60 TON | C867: H | D867: 2281.2299 | F867: 90.38 | G867: 206142.32 | H867: 0.05 | I867: 99.52 | J867: 0.01 | K867: 31.52
A868: IE5074 | B868: EMPILHADEIRA | C868: H | D868: 3968.518 | E868: 1793.956 | F868: 50 | G868: 199282.42 | H868: 0.04 | I868: 99.56 | J868: 0.01 | K868: 31.53
A869: IE5051 | B869: TUBO / FUNIL PARA CONCRETAGEM | C869: H | D869: 12792.98 | E869: 70754.684 | F869: 15.33 | G869: 196233.54 | H869: 0.04 | I869: 99.6 | J869: 0.01 | K869: 31.54
A870: IE0011 | B870: RETROESCAVADEIRA | C870: H | D870: 1899.2763 | E870: 166.567 | F870: 77.47 | G870: 151253.76 | H870: 0.03 | I870: 99.63 | J870: 0.01 | K870: 31.55
A871: IE5033 | B871: TRATOR DE ESTEIRA D150B HIDROSTATICO | C871: H | D871: 1165.5886 | F871: 125.28 | G871: 145579.65 | H871: 0.03 | I871: 99.66 | J871: 0.01 | K871: 31.56
A872: IE5042 | B872: ROLO DE PNEUS AP 26 HIDROSTATICO 24T | C872: H | D872: 1075.0941 | F872: 109.96 | G872: 118337.54 | H872: 0.03 | I872: 99.69 | J872: 0.01 | K872: 31.57
A873: IE5001 | B873: CENTRAL DOSADORA DE CONCRETO 100M3/H | C873: UN | D873: 0.099591 | F873: 1152600 | G873: 114797.36 | H873: 0.03 | I873: 99.72 | J873: 0.01 | K873: 31.58
A874: IE0111 | B874: EQUIP. DISTRIBUIÇÃO DE ASFALTO | C874: H | D874: 910.58125 | F874: 119.59 | G874: 109009.75 | H874: 0.02 | I874: 99.74 | J874: 0.01 | K874: 31.59
A875: IE0112 | B875: AQUECEDOR DE FLUIDO TÉRMICO | C875: H | D875: 1069.5718 | F875: 101.29 | G875: 108319.49 | H875: 0.02 | I875: 99.76 | J875: 0.01 | K875: 31.6
A876: IE5003 | B876: SILO DE CIMENTO METALICO 200T | C876: UN | D876: 0.497715 | F876: 207000 | G876: 102957.19 | H876: 0.02 | I876: 99.78 | J876: 0.01 | K876: 31.61
A877: IE5000 | B877: ESCAVADEIRA HIDRAULICA 2,7 M3 E385C ME- 264 HP COM ROMPEDOR | C877: H | D877: 515.05291 | E877: 30 | F877: 193.93 | G877: 101758.52 | H877: 0.02 | I877: 99.8 | J877: 0.01 | K877: 31.62
A878: IE0009 | B878: PÁ CARREGADEIRA 770-9S | C878: H | D878: 679.62877 | F878: 131.95 | G878: 89822.95 | H878: 0.02 | I878: 99.82 | J878: 0.01 | K878: 31.63
A879: IE5006 | B879: BOMBA LANÇA DE CONCRETO COMP. 36M - AQUISIÇÃO | C879: UN | D879: 0.065201 | F879: 1240000 | G879: 80859.26 | H879: 0.02 | I879: 99.84 | J879: 0.01 | K879: 31.64
A880: IE0149 | B880: ACABADORA DE ASFALTO SOBRE PNEUS | C880: H | D880: 400.67236 | E880: 26.853 | F880: 173.56 | G880: 71429.04 | H880: 0.02 | I880: 99.86 | J880: 0 | K880: 31.64
A881: IE0127 | B881: FRESADORA A FRIO : WIRTGEN : W 200 - | C881: H | D881: 75.661 | F881: 889.54 | G881: 67308.03 | H881: 0.01 | I881: 99.87 | J881: 0 | K881: 31.64
A882: IE5011 | B882: GUINDASTE 30T - MOBILIZAÇÃO | C882: VB | D882: 15.929939 | F882: 4000 | G882: 63964.07 | H882: 0.01 | I882: 99.88 | J882: 0 | K882: 31.64
A883: IE5063 | B883: GUINDASTE SOBRE PNEUS 120T - MOB+DESMOB. | C883: VB | D883: 2 | F883: 28000 | G883: 56000 | H883: 0.01 | I883: 99.89 | J883: 0 | K883: 31.64
A884: IE5081 | B884: EQUIPAMENTO MARINHO PARA COMBWALL | C884: H | D884: 12 | F884: 3519.23 | G884: 42230.8 | H884: 0.01 | I884: 99.9 | J884: 0 | K884: 31.64
A885: IE0906 | B885: PLACA VIBRATORIA | C885: H | D885: 1887.002 | F885: 20.9 | G885: 39473.6 | H885: 0.01 | I885: 99.91 | J885: 0 | K885: 31.64
A886: IE0209 | B886: MARTELETE - ROMPEDOR 28 KG | C886: H | D886: 2120.2118 | E886: 160.005 | F886: 16.68 | G886: 37845.55 | H886: 0.01 | I886: 99.92 | J886: 0 | K886: 31.64
A887: IE0102 | B887: ROLO COMPACTADOR TANDEM LISO | C887: H | D887: 289.80341 | E887: 71.951 | F887: 120.19 | G887: 37416.05 | H887: 0.01 | I887: 99.93 | J887: 0 | K887: 31.64
A888: IE0904 | B888: SERRA CIRCULAR DE BANCADA | C888: H | D888: 19727.966 | E888: 11585.98 | F888: 1.83 | G888: 36207.07 | H888: 0.01 | I888: 99.94 | J888: 0 | K888: 31.64
A889: IE0105 | B889: ROLO COMPACTADOR : CATERPILLAR : PS-360 C - DE PNEUS | C889: H | D889: 287.67882 | E889: 147.772 | F889: 114.39 | G889: 35176.95 | H889: 0.01 | I889: 99.95 | J889: 0 | K889: 31.64
A890: IE0332 | B890: TEXTURIZADORA E LANÇADORA | C890: H | D890: 299.65107 | F890: 110.36 | G890: 33039.53 | H890: 0.01 | I890: 99.96 | J890: 0 | K890: 31.64
A891: IE0110 | B891: TANQUE DE ESTOCAGEM DE ASFALTO - 30.000 L | C891: H | D891: 1684.3511 | F891: 18.52 | G891: 30307.01 | H891: 0.01 | I891: 99.97 | J891: 0 | K891: 31.64
...

Sheet CPU AUX
